System_Verilog_code_base/motoracceleration/steppermotor.sv
module steppermotor(input dir,enable,pulse, input wire signed [31:0] distance,output reg [31:0] stp);



      //coils
reg A,B,C,D;
reg [31:0] steps = 0;
      //step position
reg [3:0] p = 0;
reg [31:0] truedistance = ((200 * 2) / (2 * 8));

  always @(pulse) begin
    
      
    if(steps != truedistance) begin

  

    if(p == 4 ) begin
    
        p = 0;
        steps = steps + 1;
        stp = steps;
    
    end

    if(enable && dir) begin
        
       case(p)
        
          0 : {A, B, C, D} = {1'd1,1'd0,1'd0,1'd1};
          1 : {A, B, C, D} = {1'd1,1'd1,1'd0,1'd0};
          2 : {A, B, C, D} = {1'd0,1'd1,1'd1,1'd0};
          3 : {A, B, C, D} = {1'd0,1'd0,1'd1,1'd1};

          default: {A, B, C, D} = {1'd0,1'd0,1'd0,1'd0};
       endcase
     end 
    
     if(enable && ~dir) begin
        
        case(p)
        
          0 : {D, C, B, A} = {1'd1,1'd0,1'd0,1'd1};
          1 : {D, C, B, A} = {1'd1,1'd1,1'd0,1'd0};
          2 : {D, C, B, A} = {1'd0,1'd1,1'd1,1'd0};
          3 : {D, C, B, A} = {1'd0,1'd0,1'd1,1'd1};
          
            default: {A, B, C, D} = {1'd0,1'd0,1'd0,1'd0};
        endcase
        
     end 
    end   
     if(~enable || steps == distance) begin
     
        {A ,B ,C ,D} = {1'd0,1'd0,1'd0,1'd0};
        p = 0;
        
     end 
    p = p+1;
  end

endmodule

System_Verilog_code_base/motoracceleration/sqrt.sv
module sqrt(input RESET, PREVIOUS, NEXT, CLK, input [31:0] N , input [31:0] DELTA , output reg [63:0] m);
//input [31:0] H, input [31:0] L , input [31:0] N , input [31:0] DELTA , output reg [63:0] m);

    //internal 

    reg done;    
    
    
    reg [31:0] sqrt;
    reg [31:0] h;
    reg [31:0] l;
    reg [31:0] n;
    reg [31:0] delta;
    reg [4:0]  iterations;
    reg [63:0] current_sqrt;
    //reg [63:0] m;
    always @(posedge CLK) begin
      
      
        // apply variables initialize when PREVIOUS and NEXT are both 1
        if(PREVIOUS && NEXT) begin
         
            n = N;
            delta = DELTA;    
            iterations = 0;
            done = 0;
            sqrt = n;
            
        end
        
        if(~done) begin
        
        current_sqrt = (h + l)/2;
        
        //begin logic
        if(delta >= 2*(-16)) begin
            
            if(current_sqrt * current_sqrt > n) begin
                        
                    h = current_sqrt;
                    n = N; 
                    delta = delta / 2;
            
            end else begin
                    
                    l = current_sqrt;
                    n = N; 
                    delta = delta / 2;    
                    
            end
      
        end
        
        
        // stops after 16 iterations
        if(iterations == 16) begin
  
            done = 1;
            iterations = 0;
            
            
        end
        
         //reset signal
        if(RESET) begin
            
            sqrt = 1;
            done = 1;
            delta = 1;
            current_sqrt = 1;
        
        end
             if(NEXT) begin
            
             h = sqrt + delta;
             l = sqrt;
             n = n+1;
             delta = delta;
             sqrt = (n+1);
            
             
        end
        
        if(PREVIOUS) begin
            
            h = sqrt;
            l = sqrt - delta;
            n = n - 1;
            delta = delta;    
            sqrt = (n-1);
            
        end
         m = current_sqrt; 
            
         iterations = iterations +1; 
         
       end
              
    end
    

endmodule

project3/motoracceleration/motor_if.sv
module motor_if(input move, emergancy, clk, input [63:0] distance, input [31:0] steps, output clk_out);

reg [7:0] counter = 0;
reg pulse, next, previous, reset, enable;
reg [31:0] n;
reg [31:0] delta;

wire [63:0] delay;

//distance calculatios
reg [31:0] truedistance = ((200 * 2) / (2 * 8));

//reset timer
reg [7:0] resettime = 0;

    // the counter counts to 20 this is  a compleatly arbitrary number
    // it is just easier to work with it
    
    
    always @(posedge clk) begin

        //initializer
        if(move) begin
            
   
            
            // (steps per rebolution * microsteping factor) / (pitch * number of teeth) per milimeter
            
            // enable math
            n = 2'd01;
            delta = 4'b000_1;
            
            reset = 0;
            
        //calculate smothness
            if (resettime <= 5) begin
             next = 1; previous = 1;
             enable = 1;
            end 
            
            else begin
 
            if(steps > (truedistance)) begin 
                next = 0; previous = 1;
                end else begin
                 next = 1; previous = 0;
                end
                           
            end
                    
            if (counter <= 50) counter <= counter + 1; 
            else counter <= 0; 
            
            if (counter < delay) pulse = 1;
            else pulse = 0;
            
      end
      
      if(resettime < 6) begin
        resettime = resettime + 1;
      

      end
      
      if(steps == (truedistance - 5))begin
        resettime = 0;
      end
      
    end
    
      sqrt math(reset, previous,next, clk, n, delta, delay);
      assign clk_out = pulse;
    
endmodule

System_Verilog_code_base/motoracceleration/motor_if_tb.sv
`timescale 1ns/10ps

module motor_if_tb;


reg clk;
reg emergancy;
reg move;
reg [63:0] distance;
wire c;
wire [31:0] steps;


integer i;

initial begin
    
    
    clk = 0;
    emergancy = 0;
    move = 1;
    distance = 5'd0800;
   
    
    $dumpfile("motor_if_tb.vcd");
    $dumpvars;

    for(i = 0; i <= 8000 ; i = i+1)begin
    
    clk = ~clk; #10;
    
    end    
    
end


    motor_if motoracceleration(move, emergancy, clk, 200,steps, c );
    steppermotor motor(move, move, c, 200, steps);


endmodule

System_Verilog_code_base/motoracceleration/motor_if_tb.vcd
$date
	Thu Feb 10 21:57:05 2022
$end
$version
	Icarus Verilog
$end
$timescale
	10ps
$end
$scope module motor_if_tb $end
$var wire 32 ! steps [31:0] $end
$var wire 1 " c $end
$var reg 1 # clk $end
$var reg 64 $ distance [63:0] $end
$var reg 1 % emergancy $end
$var reg 1 & move $end
$var integer 32 ' i [31:0] $end
$scope module motor $end
$var wire 1 & dir $end
$var wire 32 ( distance [31:0] $end
$var wire 1 & enable $end
$var wire 1 " pulse $end
$var reg 1 ) A $end
$var reg 1 * B $end
$var reg 1 + C $end
$var reg 1 , D $end
$var reg 4 - p [3:0] $end
$var reg 32 . steps [31:0] $end
$var reg 32 / stp [31:0] $end
$var reg 32 0 truedistance [31:0] $end
$upscope $end
$scope module motoracceleration $end
$var wire 1 # clk $end
$var wire 1 " clk_out $end
$var wire 64 1 distance [63:0] $end
$var wire 1 % emergancy $end
$var wire 1 & move $end
$var wire 32 2 steps [31:0] $end
$var wire 64 3 delay [63:0] $end
$var reg 8 4 counter [7:0] $end
$var reg 32 5 delta [31:0] $end
$var reg 1 6 enable $end
$var reg 32 7 n [31:0] $end
$var reg 1 8 next $end
$var reg 1 9 previous $end
$var reg 1 : pulse $end
$var reg 1 ; reset $end
$var reg 8 < resettime [7:0] $end
$var reg 32 = truedistance [31:0] $end
$scope module math $end
$var wire 1 # CLK $end
$var wire 32 > DELTA [31:0] $end
$var wire 32 ? N [31:0] $end
$var wire 1 8 NEXT $end
$var wire 1 9 PREVIOUS $end
$var wire 1 ; RESET $end
$var reg 64 @ current_sqrt [63:0] $end
$var reg 32 A delta [31:0] $end
$var reg 1 B done $end
$var reg 32 C h [31:0] $end
$var reg 5 D iterations [4:0] $end
$var reg 32 E l [31:0] $end
$var reg 64 F m [63:0] $end
$var reg 32 G n [31:0] $end
$var reg 32 H sqrt [31:0] $end
$upscope $end
$upscope $end
$upscope $end
$enddefinitions $end
#0
$dumpvars
b0 H
b1 G
bx F
b10 E
b1 D
b11 C
0B
b1 A
bx @
b1 ?
b1 >
b11001 =
b1 <
0;
0:
19
18
b1 7
16
b1 5
b1 4
bx 3
bx 2
b11001000 1
b11001 0
bx /
b0 .
b1 -
1,
0+
0*
1)
b11001000 (
b0 '
1&
0%
b0 $
1#
0"
bx !
$end
#1000
0#
b1 '
#2000
b10 4
b10 -
1*
0,
b10 <
1"
1:
b10 3
b10 F
b1 G
b10 E
b11 C
b10 @
b0 H
b1 D
1#
b10 '
#3000
0#
b11 '
#4000
b11 4
b11 -
0)
1+
b1 G
b10 E
b11 C
b0 H
b1 D
b11 <
0"
0:
1#
b100 '
#5000
0#
b101 '
#6000
b100 4
b100 <
b1 G
b10 E
b11 C
b0 H
b1 D
1#
b110 '
#7000
0#
b111 '
#8000
b101 4
b1 G
b10 E
b11 C
b0 H
b1 D
b101 <
1#
b1000 '
#9000
0#
b1001 '
#10000
b110 4
b110 <
b1 G
b10 E
b11 C
b0 H
b1 D
1#
b1010 '
#11000
0#
b1011 '
#12000
b111 4
b10 D
b11 H
b10 G
b0 E
b1 C
09
1#
b1100 '
#13000
0#
b1101 '
#14000
b1000 4
b11 D
b0 3
b0 F
b100 H
b11 G
b11 E
b100 C
b0 @
1#
b1110 '
#15000
0#
b1111 '
#16000
b1001 4
b100 D
b11 3
b11 F
b101 H
b100 G
b100 E
b101 C
b11 @
1#
b10000 '
#17000
0#
b10001 '
#18000
b1010 4
b101 D
b100 3
b100 F
b110 H
b101 G
b101 E
b110 C
b100 @
1#
b10010 '
#19000
0#
b10011 '
#20000
b1011 4
b110 D
b101 3
b101 F
b111 H
b110 G
b110 E
b111 C
b101 @
1#
b10100 '
#21000
0#
b10101 '
#22000
b1100 4
b111 D
b110 3
b110 F
b1000 H
b111 G
b111 E
b1000 C
b110 @
1#
b10110 '
#23000
0#
b10111 '
#24000
b1101 4
b1000 D
b111 3
b111 F
b1001 H
b1000 G
b1000 E
b1001 C
b111 @
1#
b11000 '
#25000
0#
b11001 '
#26000
b1110 4
b1001 D
b1000 3
b1000 F
b1010 H
b1001 G
b1001 E
b1010 C
b1000 @
1#
b11010 '
#27000
0#
b11011 '
#28000
b1111 4
b1010 D
b1001 3
b1001 F
b1011 H
b1010 G
b1010 E
b1011 C
b1001 @
1#
b11100 '
#29000
0#
b11101 '
#30000
b10000 4
b1011 D
b1010 3
b1010 F
b1100 H
b1011 G
b1011 E
b1100 C
b1010 @
1#
b11110 '
#31000
0#
b11111 '
#32000
b10001 4
b1100 D
b1011 3
b1011 F
b1101 H
b1100 G
b1100 E
b1101 C
b1011 @
1#
b100000 '
#33000
0#
b100001 '
#34000
b10010 4
b1101 D
b1100 3
b1100 F
b1110 H
b1101 G
b1101 E
b1110 C
b1100 @
1#
b100010 '
#35000
0#
b100011 '
#36000
b10011 4
b1110 D
b1101 3
b1101 F
b1111 H
b1110 G
b1110 E
b1111 C
b1101 @
1#
b100100 '
#37000
0#
b100101 '
#38000
b10100 4
b1111 D
b1110 3
b1110 F
b10000 H
b1111 G
b1111 E
b10000 C
b1110 @
1#
b100110 '
#39000
0#
b100111 '
#40000
b10101 4
b10000 D
b1111 3
b1111 F
b10001 H
b10000 G
b10000 E
b10001 C
b1111 @
1#
b101000 '
#41000
0#
b101001 '
#42000
b10110 4
b10000 3
b10000 F
b10010 H
b10001 G
b10001 E
b10010 C
b1 D
1B
b10000 @
1#
b101010 '
#43000
0#
b101011 '
#44000
b10111 4
1#
b101100 '
#45000
0#
b101101 '
#46000
b11000 4
1#
b101110 '
#47000
0#
b101111 '
#48000
b11001 4
1#
b110000 '
#49000
0#
b110001 '
#50000
b11010 4
1#
b110010 '
#51000
0#
b110011 '
#52000
b11011 4
1#
b110100 '
#53000
0#
b110101 '
#54000
b11100 4
1#
b110110 '
#55000
0#
b110111 '
#56000
b11101 4
1#
b111000 '
#57000
0#
b111001 '
#58000
b11110 4
1#
b111010 '
#59000
0#
b111011 '
#60000
b11111 4
1#
b111100 '
#61000
0#
b111101 '
#62000
b100000 4
1#
b111110 '
#63000
0#
b111111 '
#64000
b100001 4
1#
b1000000 '
#65000
0#
b1000001 '
#66000
b100010 4
1#
b1000010 '
#67000
0#
b1000011 '
#68000
b100011 4
1#
b1000100 '
#69000
0#
b1000101 '
#70000
b100100 4
1#
b1000110 '
#71000
0#
b1000111 '
#72000
b100101 4
1#
b1001000 '
#73000
0#
b1001001 '
#74000
b100110 4
1#
b1001010 '
#75000
0#
b1001011 '
#76000
b100111 4
1#
b1001100 '
#77000
0#
b1001101 '
#78000
b101000 4
1#
b1001110 '
#79000
0#
b1001111 '
#80000
b101001 4
1#
b1010000 '
#81000
0#
b1010001 '
#82000
b101010 4
1#
b1010010 '
#83000
0#
b1010011 '
#84000
b101011 4
1#
b1010100 '
#85000
0#
b1010101 '
#86000
b101100 4
1#
b1010110 '
#87000
0#
b1010111 '
#88000
b101101 4
1#
b1011000 '
#89000
0#
b1011001 '
#90000
b101110 4
1#
b1011010 '
#91000
0#
b1011011 '
#92000
b101111 4
1#
b1011100 '
#93000
0#
b1011101 '
#94000
b110000 4
1#
b1011110 '
#95000
0#
b1011111 '
#96000
b110001 4
1#
b1100000 '
#97000
0#
b1100001 '
#98000
b110010 4
1#
b1100010 '
#99000
0#
b1100011 '
#100000
b110011 4
1#
b1100100 '
#101000
0#
b1100101 '
#102000
b0 4
1#
b1100110 '
#103000
0#
b1100111 '
#104000
b1 4
b100 -
0*
1,
1"
1:
1#
b1101000 '
#105000
0#
b1101001 '
#106000
b10 4
1#
b1101010 '
#107000
0#
b1101011 '
#108000
b11 4
1#
b1101100 '
#109000
0#
b1101101 '
#110000
b100 4
1#
b1101110 '
#111000
0#
b1101111 '
#112000
b101 4
1#
b1110000 '
#113000
0#
b1110001 '
#114000
b110 4
1#
b1110010 '
#115000
0#
b1110011 '
#116000
b111 4
1#
b1110100 '
#117000
0#
b1110101 '
#118000
b1000 4
1#
b1110110 '
#119000
0#
b1110111 '
#120000
b1001 4
1#
b1111000 '
#121000
0#
b1111001 '
#122000
b1010 4
1#
b1111010 '
#123000
0#
b1111011 '
#124000
b1011 4
1#
b1111100 '
#125000
0#
b1111101 '
#126000
b1100 4
1#
b1111110 '
#127000
0#
b1111111 '
#128000
b1101 4
1#
b10000000 '
#129000
0#
b10000001 '
#130000
b1110 4
1#
b10000010 '
#131000
0#
b10000011 '
#132000
b1111 4
1#
b10000100 '
#133000
0#
b10000101 '
#134000
b10000 4
1#
b10000110 '
#135000
0#
b10000111 '
#136000
b10001 4
1)
0+
b1 !
b1 /
b1 2
b1 .
b1 -
0"
0:
1#
b10001000 '
#137000
0#
b10001001 '
#138000
b10010 4
1#
b10001010 '
#139000
0#
b10001011 '
#140000
b10011 4
1#
b10001100 '
#141000
0#
b10001101 '
#142000
b10100 4
1#
b10001110 '
#143000
0#
b10001111 '
#144000
b10101 4
1#
b10010000 '
#145000
0#
b10010001 '
#146000
b10110 4
1#
b10010010 '
#147000
0#
b10010011 '
#148000
b10111 4
1#
b10010100 '
#149000
0#
b10010101 '
#150000
b11000 4
1#
b10010110 '
#151000
0#
b10010111 '
#152000
b11001 4
1#
b10011000 '
#153000
0#
b10011001 '
#154000
b11010 4
1#
b10011010 '
#155000
0#
b10011011 '
#156000
b11011 4
1#
b10011100 '
#157000
0#
b10011101 '
#158000
b11100 4
1#
b10011110 '
#159000
0#
b10011111 '
#160000
b11101 4
1#
b10100000 '
#161000
0#
b10100001 '
#162000
b11110 4
1#
b10100010 '
#163000
0#
b10100011 '
#164000
b11111 4
1#
b10100100 '
#165000
0#
b10100101 '
#166000
b100000 4
1#
b10100110 '
#167000
0#
b10100111 '
#168000
b100001 4
1#
b10101000 '
#169000
0#
b10101001 '
#170000
b100010 4
1#
b10101010 '
#171000
0#
b10101011 '
#172000
b100011 4
1#
b10101100 '
#173000
0#
b10101101 '
#174000
b100100 4
1#
b10101110 '
#175000
0#
b10101111 '
#176000
b100101 4
1#
b10110000 '
#177000
0#
b10110001 '
#178000
b100110 4
1#
b10110010 '
#179000
0#
b10110011 '
#180000
b100111 4
1#
b10110100 '
#181000
0#
b10110101 '
#182000
b101000 4
1#
b10110110 '
#183000
0#
b10110111 '
#184000
b101001 4
1#
b10111000 '
#185000
0#
b10111001 '
#186000
b101010 4
1#
b10111010 '
#187000
0#
b10111011 '
#188000
b101011 4
1#
b10111100 '
#189000
0#
b10111101 '
#190000
b101100 4
1#
b10111110 '
#191000
0#
b10111111 '
#192000
b101101 4
1#
b11000000 '
#193000
0#
b11000001 '
#194000
b101110 4
1#
b11000010 '
#195000
0#
b11000011 '
#196000
b101111 4
1#
b11000100 '
#197000
0#
b11000101 '
#198000
b110000 4
1#
b11000110 '
#199000
0#
b11000111 '
#200000
b110001 4
1#
b11001000 '
#201000
0#
b11001001 '
#202000
b110010 4
1#
b11001010 '
#203000
0#
b11001011 '
#204000
b110011 4
1#
b11001100 '
#205000
0#
b11001101 '
#206000
b0 4
1#
b11001110 '
#207000
0#
b11001111 '
#208000
b1 4
b10 -
1*
0,
1"
1:
1#
b11010000 '
#209000
0#
b11010001 '
#210000
b10 4
1#
b11010010 '
#211000
0#
b11010011 '
#212000
b11 4
1#
b11010100 '
#213000
0#
b11010101 '
#214000
b100 4
1#
b11010110 '
#215000
0#
b11010111 '
#216000
b101 4
1#
b11011000 '
#217000
0#
b11011001 '
#218000
b110 4
1#
b11011010 '
#219000
0#
b11011011 '
#220000
b111 4
1#
b11011100 '
#221000
0#
b11011101 '
#222000
b1000 4
1#
b11011110 '
#223000
0#
b11011111 '
#224000
b1001 4
1#
b11100000 '
#225000
0#
b11100001 '
#226000
b1010 4
1#
b11100010 '
#227000
0#
b11100011 '
#228000
b1011 4
1#
b11100100 '
#229000
0#
b11100101 '
#230000
b1100 4
1#
b11100110 '
#231000
0#
b11100111 '
#232000
b1101 4
1#
b11101000 '
#233000
0#
b11101001 '
#234000
b1110 4
1#
b11101010 '
#235000
0#
b11101011 '
#236000
b1111 4
1#
b11101100 '
#237000
0#
b11101101 '
#238000
b10000 4
1#
b11101110 '
#239000
0#
b11101111 '
#240000
b10001 4
b11 -
0)
1+
0"
0:
1#
b11110000 '
#241000
0#
b11110001 '
#242000
b10010 4
1#
b11110010 '
#243000
0#
b11110011 '
#244000
b10011 4
1#
b11110100 '
#245000
0#
b11110101 '
#246000
b10100 4
1#
b11110110 '
#247000
0#
b11110111 '
#248000
b10101 4
1#
b11111000 '
#249000
0#
b11111001 '
#250000
b10110 4
1#
b11111010 '
#251000
0#
b11111011 '
#252000
b10111 4
1#
b11111100 '
#253000
0#
b11111101 '
#254000
b11000 4
1#
b11111110 '
#255000
0#
b11111111 '
#256000
b11001 4
1#
b100000000 '
#257000
0#
b100000001 '
#258000
b11010 4
1#
b100000010 '
#259000
0#
b100000011 '
#260000
b11011 4
1#
b100000100 '
#261000
0#
b100000101 '
#262000
b11100 4
1#
b100000110 '
#263000
0#
b100000111 '
#264000
b11101 4
1#
b100001000 '
#265000
0#
b100001001 '
#266000
b11110 4
1#
b100001010 '
#267000
0#
b100001011 '
#268000
b11111 4
1#
b100001100 '
#269000
0#
b100001101 '
#270000
b100000 4
1#
b100001110 '
#271000
0#
b100001111 '
#272000
b100001 4
1#
b100010000 '
#273000
0#
b100010001 '
#274000
b100010 4
1#
b100010010 '
#275000
0#
b100010011 '
#276000
b100011 4
1#
b100010100 '
#277000
0#
b100010101 '
#278000
b100100 4
1#
b100010110 '
#279000
0#
b100010111 '
#280000
b100101 4
1#
b100011000 '
#281000
0#
b100011001 '
#282000
b100110 4
1#
b100011010 '
#283000
0#
b100011011 '
#284000
b100111 4
1#
b100011100 '
#285000
0#
b100011101 '
#286000
b101000 4
1#
b100011110 '
#287000
0#
b100011111 '
#288000
b101001 4
1#
b100100000 '
#289000
0#
b100100001 '
#290000
b101010 4
1#
b100100010 '
#291000
0#
b100100011 '
#292000
b101011 4
1#
b100100100 '
#293000
0#
b100100101 '
#294000
b101100 4
1#
b100100110 '
#295000
0#
b100100111 '
#296000
b101101 4
1#
b100101000 '
#297000
0#
b100101001 '
#298000
b101110 4
1#
b100101010 '
#299000
0#
b100101011 '
#300000
b101111 4
1#
b100101100 '
#301000
0#
b100101101 '
#302000
b110000 4
1#
b100101110 '
#303000
0#
b100101111 '
#304000
b110001 4
1#
b100110000 '
#305000
0#
b100110001 '
#306000
b110010 4
1#
b100110010 '
#307000
0#
b100110011 '
#308000
b110011 4
1#
b100110100 '
#309000
0#
b100110101 '
#310000
b0 4
1#
b100110110 '
#311000
0#
b100110111 '
#312000
b1 4
b100 -
0*
1,
1"
1:
1#
b100111000 '
#313000
0#
b100111001 '
#314000
b10 4
1#
b100111010 '
#315000
0#
b100111011 '
#316000
b11 4
1#
b100111100 '
#317000
0#
b100111101 '
#318000
b100 4
1#
b100111110 '
#319000
0#
b100111111 '
#320000
b101 4
1#
b101000000 '
#321000
0#
b101000001 '
#322000
b110 4
1#
b101000010 '
#323000
0#
b101000011 '
#324000
b111 4
1#
b101000100 '
#325000
0#
b101000101 '
#326000
b1000 4
1#
b101000110 '
#327000
0#
b101000111 '
#328000
b1001 4
1#
b101001000 '
#329000
0#
b101001001 '
#330000
b1010 4
1#
b101001010 '
#331000
0#
b101001011 '
#332000
b1011 4
1#
b101001100 '
#333000
0#
b101001101 '
#334000
b1100 4
1#
b101001110 '
#335000
0#
b101001111 '
#336000
b1101 4
1#
b101010000 '
#337000
0#
b101010001 '
#338000
b1110 4
1#
b101010010 '
#339000
0#
b101010011 '
#340000
b1111 4
1#
b101010100 '
#341000
0#
b101010101 '
#342000
b10000 4
1#
b101010110 '
#343000
0#
b101010111 '
#344000
b10001 4
1)
0+
b10 !
b10 /
b10 2
b10 .
b1 -
0"
0:
1#
b101011000 '
#345000
0#
b101011001 '
#346000
b10010 4
1#
b101011010 '
#347000
0#
b101011011 '
#348000
b10011 4
1#
b101011100 '
#349000
0#
b101011101 '
#350000
b10100 4
1#
b101011110 '
#351000
0#
b101011111 '
#352000
b10101 4
1#
b101100000 '
#353000
0#
b101100001 '
#354000
b10110 4
1#
b101100010 '
#355000
0#
b101100011 '
#356000
b10111 4
1#
b101100100 '
#357000
0#
b101100101 '
#358000
b11000 4
1#
b101100110 '
#359000
0#
b101100111 '
#360000
b11001 4
1#
b101101000 '
#361000
0#
b101101001 '
#362000
b11010 4
1#
b101101010 '
#363000
0#
b101101011 '
#364000
b11011 4
1#
b101101100 '
#365000
0#
b101101101 '
#366000
b11100 4
1#
b101101110 '
#367000
0#
b101101111 '
#368000
b11101 4
1#
b101110000 '
#369000
0#
b101110001 '
#370000
b11110 4
1#
b101110010 '
#371000
0#
b101110011 '
#372000
b11111 4
1#
b101110100 '
#373000
0#
b101110101 '
#374000
b100000 4
1#
b101110110 '
#375000
0#
b101110111 '
#376000
b100001 4
1#
b101111000 '
#377000
0#
b101111001 '
#378000
b100010 4
1#
b101111010 '
#379000
0#
b101111011 '
#380000
b100011 4
1#
b101111100 '
#381000
0#
b101111101 '
#382000
b100100 4
1#
b101111110 '
#383000
0#
b101111111 '
#384000
b100101 4
1#
b110000000 '
#385000
0#
b110000001 '
#386000
b100110 4
1#
b110000010 '
#387000
0#
b110000011 '
#388000
b100111 4
1#
b110000100 '
#389000
0#
b110000101 '
#390000
b101000 4
1#
b110000110 '
#391000
0#
b110000111 '
#392000
b101001 4
1#
b110001000 '
#393000
0#
b110001001 '
#394000
b101010 4
1#
b110001010 '
#395000
0#
b110001011 '
#396000
b101011 4
1#
b110001100 '
#397000
0#
b110001101 '
#398000
b101100 4
1#
b110001110 '
#399000
0#
b110001111 '
#400000
b101101 4
1#
b110010000 '
#401000
0#
b110010001 '
#402000
b101110 4
1#
b110010010 '
#403000
0#
b110010011 '
#404000
b101111 4
1#
b110010100 '
#405000
0#
b110010101 '
#406000
b110000 4
1#
b110010110 '
#407000
0#
b110010111 '
#408000
b110001 4
1#
b110011000 '
#409000
0#
b110011001 '
#410000
b110010 4
1#
b110011010 '
#411000
0#
b110011011 '
#412000
b110011 4
1#
b110011100 '
#413000
0#
b110011101 '
#414000
b0 4
1#
b110011110 '
#415000
0#
b110011111 '
#416000
b1 4
b10 -
1*
0,
1"
1:
1#
b110100000 '
#417000
0#
b110100001 '
#418000
b10 4
1#
b110100010 '
#419000
0#
b110100011 '
#420000
b11 4
1#
b110100100 '
#421000
0#
b110100101 '
#422000
b100 4
1#
b110100110 '
#423000
0#
b110100111 '
#424000
b101 4
1#
b110101000 '
#425000
0#
b110101001 '
#426000
b110 4
1#
b110101010 '
#427000
0#
b110101011 '
#428000
b111 4
1#
b110101100 '
#429000
0#
b110101101 '
#430000
b1000 4
1#
b110101110 '
#431000
0#
b110101111 '
#432000
b1001 4
1#
b110110000 '
#433000
0#
b110110001 '
#434000
b1010 4
1#
b110110010 '
#435000
0#
b110110011 '
#436000
b1011 4
1#
b110110100 '
#437000
0#
b110110101 '
#438000
b1100 4
1#
b110110110 '
#439000
0#
b110110111 '
#440000
b1101 4
1#
b110111000 '
#441000
0#
b110111001 '
#442000
b1110 4
1#
b110111010 '
#443000
0#
b110111011 '
#444000
b1111 4
1#
b110111100 '
#445000
0#
b110111101 '
#446000
b10000 4
1#
b110111110 '
#447000
0#
b110111111 '
#448000
b10001 4
b11 -
0)
1+
0"
0:
1#
b111000000 '
#449000
0#
b111000001 '
#450000
b10010 4
1#
b111000010 '
#451000
0#
b111000011 '
#452000
b10011 4
1#
b111000100 '
#453000
0#
b111000101 '
#454000
b10100 4
1#
b111000110 '
#455000
0#
b111000111 '
#456000
b10101 4
1#
b111001000 '
#457000
0#
b111001001 '
#458000
b10110 4
1#
b111001010 '
#459000
0#
b111001011 '
#460000
b10111 4
1#
b111001100 '
#461000
0#
b111001101 '
#462000
b11000 4
1#
b111001110 '
#463000
0#
b111001111 '
#464000
b11001 4
1#
b111010000 '
#465000
0#
b111010001 '
#466000
b11010 4
1#
b111010010 '
#467000
0#
b111010011 '
#468000
b11011 4
1#
b111010100 '
#469000
0#
b111010101 '
#470000
b11100 4
1#
b111010110 '
#471000
0#
b111010111 '
#472000
b11101 4
1#
b111011000 '
#473000
0#
b111011001 '
#474000
b11110 4
1#
b111011010 '
#475000
0#
b111011011 '
#476000
b11111 4
1#
b111011100 '
#477000
0#
b111011101 '
#478000
b100000 4
1#
b111011110 '
#479000
0#
b111011111 '
#480000
b100001 4
1#
b111100000 '
#481000
0#
b111100001 '
#482000
b100010 4
1#
b111100010 '
#483000
0#
b111100011 '
#484000
b100011 4
1#
b111100100 '
#485000
0#
b111100101 '
#486000
b100100 4
1#
b111100110 '
#487000
0#
b111100111 '
#488000
b100101 4
1#
b111101000 '
#489000
0#
b111101001 '
#490000
b100110 4
1#
b111101010 '
#491000
0#
b111101011 '
#492000
b100111 4
1#
b111101100 '
#493000
0#
b111101101 '
#494000
b101000 4
1#
b111101110 '
#495000
0#
b111101111 '
#496000
b101001 4
1#
b111110000 '
#497000
0#
b111110001 '
#498000
b101010 4
1#
b111110010 '
#499000
0#
b111110011 '
#500000
b101011 4
1#
b111110100 '
#501000
0#
b111110101 '
#502000
b101100 4
1#
b111110110 '
#503000
0#
b111110111 '
#504000
b101101 4
1#
b111111000 '
#505000
0#
b111111001 '
#506000
b101110 4
1#
b111111010 '
#507000
0#
b111111011 '
#508000
b101111 4
1#
b111111100 '
#509000
0#
b111111101 '
#510000
b110000 4
1#
b111111110 '
#511000
0#
b111111111 '
#512000
b110001 4
1#
b1000000000 '
#513000
0#
b1000000001 '
#514000
b110010 4
1#
b1000000010 '
#515000
0#
b1000000011 '
#516000
b110011 4
1#
b1000000100 '
#517000
0#
b1000000101 '
#518000
b0 4
1#
b1000000110 '
#519000
0#
b1000000111 '
#520000
b1 4
b100 -
0*
1,
1"
1:
1#
b1000001000 '
#521000
0#
b1000001001 '
#522000
b10 4
1#
b1000001010 '
#523000
0#
b1000001011 '
#524000
b11 4
1#
b1000001100 '
#525000
0#
b1000001101 '
#526000
b100 4
1#
b1000001110 '
#527000
0#
b1000001111 '
#528000
b101 4
1#
b1000010000 '
#529000
0#
b1000010001 '
#530000
b110 4
1#
b1000010010 '
#531000
0#
b1000010011 '
#532000
b111 4
1#
b1000010100 '
#533000
0#
b1000010101 '
#534000
b1000 4
1#
b1000010110 '
#535000
0#
b1000010111 '
#536000
b1001 4
1#
b1000011000 '
#537000
0#
b1000011001 '
#538000
b1010 4
1#
b1000011010 '
#539000
0#
b1000011011 '
#540000
b1011 4
1#
b1000011100 '
#541000
0#
b1000011101 '
#542000
b1100 4
1#
b1000011110 '
#543000
0#
b1000011111 '
#544000
b1101 4
1#
b1000100000 '
#545000
0#
b1000100001 '
#546000
b1110 4
1#
b1000100010 '
#547000
0#
b1000100011 '
#548000
b1111 4
1#
b1000100100 '
#549000
0#
b1000100101 '
#550000
b10000 4
1#
b1000100110 '
#551000
0#
b1000100111 '
#552000
b10001 4
1)
0+
b11 !
b11 /
b11 2
b11 .
b1 -
0"
0:
1#
b1000101000 '
#553000
0#
b1000101001 '
#554000
b10010 4
1#
b1000101010 '
#555000
0#
b1000101011 '
#556000
b10011 4
1#
b1000101100 '
#557000
0#
b1000101101 '
#558000
b10100 4
1#
b1000101110 '
#559000
0#
b1000101111 '
#560000
b10101 4
1#
b1000110000 '
#561000
0#
b1000110001 '
#562000
b10110 4
1#
b1000110010 '
#563000
0#
b1000110011 '
#564000
b10111 4
1#
b1000110100 '
#565000
0#
b1000110101 '
#566000
b11000 4
1#
b1000110110 '
#567000
0#
b1000110111 '
#568000
b11001 4
1#
b1000111000 '
#569000
0#
b1000111001 '
#570000
b11010 4
1#
b1000111010 '
#571000
0#
b1000111011 '
#572000
b11011 4
1#
b1000111100 '
#573000
0#
b1000111101 '
#574000
b11100 4
1#
b1000111110 '
#575000
0#
b1000111111 '
#576000
b11101 4
1#
b1001000000 '
#577000
0#
b1001000001 '
#578000
b11110 4
1#
b1001000010 '
#579000
0#
b1001000011 '
#580000
b11111 4
1#
b1001000100 '
#581000
0#
b1001000101 '
#582000
b100000 4
1#
b1001000110 '
#583000
0#
b1001000111 '
#584000
b100001 4
1#
b1001001000 '
#585000
0#
b1001001001 '
#586000
b100010 4
1#
b1001001010 '
#587000
0#
b1001001011 '
#588000
b100011 4
1#
b1001001100 '
#589000
0#
b1001001101 '
#590000
b100100 4
1#
b1001001110 '
#591000
0#
b1001001111 '
#592000
b100101 4
1#
b1001010000 '
#593000
0#
b1001010001 '
#594000
b100110 4
1#
b1001010010 '
#595000
0#
b1001010011 '
#596000
b100111 4
1#
b1001010100 '
#597000
0#
b1001010101 '
#598000
b101000 4
1#
b1001010110 '
#599000
0#
b1001010111 '
#600000
b101001 4
1#
b1001011000 '
