project3/light_controller/sensor_if.sv
module sensor_if(input sens_active,reset,clk,output passed);

reg [255-1:0] shift_reg;
reg compleated,uninterupted;

  always @(posedge clk) begin

  if(~reset && sens_active && ~uninterupted)begin

      shift_reg <= {shift_reg[255-2:0], sens_active};

      if(shift_reg[255-1])begin
        uninterupted = 1;
        shift_reg <= 0;
      end
    end  

    if(~reset && uninterupted && ~sens_active)begin
      
      shift_reg <= {shift_reg[255-2:0], ~sens_active};

    end if(uninterupted && shift_reg[255-1] && ~sens_active) begin
    
      compleated = 1;
    
    end

    if(reset) begin
      shift_reg <= 0;
      compleated = 0;
      uninterupted = 0;
    end
  end
  
  assign passed = compleated;

endmodule

System_Verilog_code_base/light_controller/sensor_if_tb.sv
`timescale 1ns/10ps

module sensor_if_tb;

reg sens_active,reset,clk;
wire passed;

integer i;

initial begin

  $dumpfile("sensor_if_tb.vcd");
  $dumpvars;


  sens_active = 1;
  reset = 0;
  clk = 0;

  for(i = 0 ; i < 5000 ; i = i+1) begin
    clk = ~clk; #10;
    if(i >= 400 && i <= 410)begin
        reset = 1;
      end else begin
        reset = 0;
      end
      if (i >= 1000)begin
        sens_active = 0;
      end

  end
  
end

sensor_if sensor(sens_active,reset,clk,passed);

endmodule

project3/light_controller/sensor_if_tb.vcd
$date
	Sun Feb  6 19:48:12 2022
$end
$version
	Icarus Verilog
$end
$timescale
	10ps
$end
$scope module sensor_if_tb $end
$var wire 1 ! passed $end
$var reg 1 " clk $end
$var reg 1 # reset $end
$var reg 1 $ sens_active $end
$var integer 32 % i [31:0] $end
$scope module sensor $end
$var wire 1 " clk $end
$var wire 1 ! passed $end
$var wire 1 # reset $end
$var wire 1 $ sens_active $end
$var reg 1 & compleated $end
$var reg 255 ' shift_reg [254:0] $end
$var reg 1 ( uninterupted $end
$upscope $end
$upscope $end
$enddefinitions $end
#0
$dumpvars
x(
bx '
x&
b0 %
1$
0#
1"
x!
$end
#1000
0"
b1 %
#2000
1"
b10 %
#3000
0"
b11 %
#4000
1"
b100 %
#5000
0"
b101 %
#6000
1"
b110 %
#7000
0"
b111 %
#8000
1"
b1000 %
#9000
0"
b1001 %
#10000
1"
b1010 %
#11000
0"
b1011 %
#12000
1"
b1100 %
#13000
0"
b1101 %
#14000
1"
b1110 %
#15000
0"
b1111 %
#16000
1"
b10000 %
#17000
0"
b10001 %
#18000
1"
b10010 %
#19000
0"
b10011 %
#20000
1"
b10100 %
#21000
0"
b10101 %
#22000
1"
b10110 %
#23000
0"
b10111 %
#24000
1"
b11000 %
#25000
0"
b11001 %
#26000
1"
b11010 %
#27000
0"
b11011 %
#28000
1"
b11100 %
#29000
0"
b11101 %
#30000
1"
b11110 %
#31000
0"
b11111 %
#32000
1"
b100000 %
#33000
0"
b100001 %
#34000
1"
b100010 %
#35000
0"
b100011 %
#36000
1"
b100100 %
#37000
0"
b100101 %
#38000
1"
b100110 %
#39000
0"
b100111 %
#40000
1"
b101000 %
#41000
0"
b101001 %
#42000
1"
b101010 %
#43000
0"
b101011 %
#44000
1"
b101100 %
#45000
0"
b101101 %
#46000
1"
b101110 %
#47000
0"
b101111 %
#48000
1"
b110000 %
#49000
0"
b110001 %
#50000
1"
b110010 %
#51000
0"
b110011 %
#52000
1"
b110100 %
#53000
0"
b110101 %
#54000
1"
b110110 %
#55000
0"
b110111 %
#56000
1"
b111000 %
#57000
0"
b111001 %
#58000
1"
b111010 %
#59000
0"
b111011 %
#60000
1"
b111100 %
#61000
0"
b111101 %
#62000
1"
b111110 %
#63000
0"
b111111 %
#64000
1"
b1000000 %
#65000
0"
b1000001 %
#66000
1"
b1000010 %
#67000
0"
b1000011 %
#68000
1"
b1000100 %
#69000
0"
b1000101 %
#70000
1"
b1000110 %
#71000
0"
b1000111 %
#72000
1"
b1001000 %
#73000
0"
b1001001 %
#74000
1"
b1001010 %
#75000
0"
b1001011 %
#76000
1"
b1001100 %
#77000
0"
b1001101 %
#78000
1"
b1001110 %
#79000
0"
b1001111 %
#80000
1"
b1010000 %
#81000
0"
b1010001 %
#82000
1"
b1010010 %
#83000
0"
b1010011 %
#84000
1"
b1010100 %
#85000
0"
b1010101 %
#86000
1"
b1010110 %
#87000
0"
b1010111 %
#88000
1"
b1011000 %
#89000
0"
b1011001 %
#90000
1"
b1011010 %
#91000
0"
b1011011 %
#92000
1"
b1011100 %
#93000
0"
b1011101 %
#94000
1"
b1011110 %
#95000
0"
b1011111 %
#96000
1"
b1100000 %
#97000
0"
b1100001 %
#98000
1"
b1100010 %
#99000
0"
b1100011 %
#100000
1"
b1100100 %
#101000
0"
b1100101 %
#102000
1"
b1100110 %
#103000
0"
b1100111 %
#104000
1"
b1101000 %
#105000
0"
b1101001 %
#106000
1"
b1101010 %
#107000
0"
b1101011 %
#108000
1"
b1101100 %
#109000
0"
b1101101 %
#110000
1"
b1101110 %
#111000
0"
b1101111 %
#112000
1"
b1110000 %
#113000
0"
b1110001 %
#114000
1"
b1110010 %
#115000
0"
b1110011 %
#116000
1"
b1110100 %
#117000
0"
b1110101 %
#118000
1"
b1110110 %
#119000
0"
b1110111 %
#120000
1"
b1111000 %
#121000
0"
b1111001 %
#122000
1"
b1111010 %
#123000
0"
b1111011 %
#124000
1"
b1111100 %
#125000
0"
b1111101 %
#126000
1"
b1111110 %
#127000
0"
b1111111 %
#128000
1"
b10000000 %
#129000
0"
b10000001 %
#130000
1"
b10000010 %
#131000
0"
b10000011 %
#132000
1"
b10000100 %
#133000
0"
b10000101 %
#134000
1"
b10000110 %
#135000
0"
b10000111 %
#136000
1"
b10001000 %
#137000
0"
b10001001 %
#138000
1"
b10001010 %
#139000
0"
b10001011 %
#140000
1"
b10001100 %
#141000
0"
b10001101 %
#142000
1"
b10001110 %
#143000
0"
b10001111 %
#144000
1"
b10010000 %
#145000
0"
b10010001 %
#146000
1"
b10010010 %
#147000
0"
b10010011 %
#148000
1"
b10010100 %
#149000
0"
b10010101 %
#150000
1"
b10010110 %
#151000
0"
b10010111 %
#152000
1"
b10011000 %
#153000
0"
b10011001 %
#154000
1"
b10011010 %
#155000
0"
b10011011 %
#156000
1"
b10011100 %
#157000
0"
b10011101 %
#158000
1"
b10011110 %
#159000
0"
b10011111 %
#160000
1"
b10100000 %
#161000
0"
b10100001 %
#162000
1"
b10100010 %
#163000
0"
b10100011 %
#164000
1"
b10100100 %
#165000
0"
b10100101 %
#166000
1"
b10100110 %
#167000
0"
b10100111 %
#168000
1"
b10101000 %
#169000
0"
b10101001 %
#170000
1"
b10101010 %
#171000
0"
b10101011 %
#172000
1"
b10101100 %
#173000
0"
b10101101 %
#174000
1"
b10101110 %
#175000
0"
b10101111 %
#176000
1"
b10110000 %
#177000
0"
b10110001 %
#178000
1"
b10110010 %
#179000
0"
b10110011 %
#180000
1"
b10110100 %
#181000
0"
b10110101 %
#182000
1"
b10110110 %
#183000
0"
b10110111 %
#184000
1"
b10111000 %
#185000
0"
b10111001 %
#186000
1"
b10111010 %
#187000
0"
b10111011 %
#188000
1"
b10111100 %
#189000
0"
b10111101 %
#190000
1"
b10111110 %
#191000
0"
b10111111 %
#192000
1"
b11000000 %
#193000
0"
b11000001 %
#194000
1"
b11000010 %
#195000
0"
b11000011 %
#196000
1"
b11000100 %
#197000
0"
b11000101 %
#198000
1"
b11000110 %
#199000
0"
b11000111 %
#200000
1"
b11001000 %
#201000
0"
b11001001 %
#202000
1"
b11001010 %
#203000
0"
b11001011 %
#204000
1"
b11001100 %
#205000
0"
b11001101 %
#206000
1"
b11001110 %
#207000
0"
b11001111 %
#208000
1"
b11010000 %
#209000
0"
b11010001 %
#210000
1"
b11010010 %
#211000
0"
b11010011 %
#212000
1"
b11010100 %
#213000
0"
b11010101 %
#214000
1"
b11010110 %
#215000
0"
b11010111 %
#216000
1"
b11011000 %
#217000
0"
b11011001 %
#218000
1"
b11011010 %
#219000
0"
b11011011 %
#220000
1"
b11011100 %
#221000
0"
b11011101 %
#222000
1"
b11011110 %
#223000
0"
b11011111 %
#224000
1"
b11100000 %
#225000
0"
b11100001 %
#226000
1"
b11100010 %
#227000
0"
b11100011 %
#228000
1"
b11100100 %
#229000
0"
b11100101 %
#230000
1"
b11100110 %
#231000
0"
b11100111 %
#232000
1"
b11101000 %
#233000
0"
b11101001 %
#234000
1"
b11101010 %
#235000
0"
b11101011 %
#236000
1"
b11101100 %
#237000
0"
b11101101 %
#238000
1"
b11101110 %
#239000
0"
b11101111 %
#240000
1"
b11110000 %
#241000
0"
b11110001 %
#242000
1"
b11110010 %
#243000
0"
b11110011 %
#244000
1"
b11110100 %
#245000
0"
b11110101 %
#246000
1"
b11110110 %
#247000
0"
b11110111 %
#248000
1"
b11111000 %
#249000
0"
b11111001 %
#250000
1"
b11111010 %
#251000
0"
b11111011 %
#252000
1"
b11111100 %
#253000
0"
b11111101 %
#254000
1"
b11111110 %
#255000
0"
b11111111 %
#256000
1"
b100000000 %
#257000
0"
b100000001 %
#258000
1"
b100000010 %
#259000
0"
b100000011 %
#260000
1"
b100000100 %
#261000
0"
b100000101 %
#262000
1"
b100000110 %
#263000
0"
b100000111 %
#264000
1"
b100001000 %
#265000
0"
b100001001 %
#266000
1"
b100001010 %
#267000
0"
b100001011 %
#268000
1"
b100001100 %
#269000
0"
b100001101 %
#270000
1"
b100001110 %
#271000
0"
b100001111 %
#272000
1"
b100010000 %
#273000
0"
b100010001 %
#274000
1"
b100010010 %
#275000
0"
b100010011 %
#276000
1"
b100010100 %
#277000
0"
b100010101 %
#278000
1"
b100010110 %
#279000
0"
b100010111 %
#280000
1"
b100011000 %
#281000
0"
b100011001 %
#282000
1"
b100011010 %
#283000
0"
b100011011 %
#284000
1"
b100011100 %
#285000
0"
b100011101 %
#286000
1"
b100011110 %
#287000
0"
b100011111 %
#288000
1"
b100100000 %
#289000
0"
b100100001 %
#290000
1"
b100100010 %
#291000
0"
b100100011 %
#292000
1"
b100100100 %
#293000
0"
b100100101 %
#294000
1"
b100100110 %
#295000
0"
b100100111 %
#296000
1"
b100101000 %
#297000
0"
b100101001 %
#298000
1"
b100101010 %
#299000
0"
b100101011 %
#300000
1"
b100101100 %
#301000
0"
b100101101 %
#302000
1"
b100101110 %
#303000
0"
b100101111 %
#304000
1"
b100110000 %
#305000
0"
b100110001 %
#306000
1"
b100110010 %
#307000
0"
b100110011 %
#308000
1"
b100110100 %
#309000
0"
b100110101 %
#310000
1"
b100110110 %
#311000
0"
b100110111 %
#312000
1"
b100111000 %
#313000
0"
b100111001 %
#314000
1"
b100111010 %
#315000
0"
b100111011 %
#316000
1"
b100111100 %
#317000
0"
b100111101 %
#318000
1"
b100111110 %
#319000
0"
b100111111 %
#320000
1"
b101000000 %
#321000
0"
b101000001 %
#322000
1"
b101000010 %
#323000
0"
b101000011 %
#324000
1"
b101000100 %
#325000
0"
b101000101 %
#326000
1"
b101000110 %
#327000
0"
b101000111 %
#328000
1"
b101001000 %
#329000
0"
b101001001 %
#330000
1"
b101001010 %
#331000
0"
b101001011 %
#332000
1"
b101001100 %
#333000
0"
b101001101 %
#334000
1"
b101001110 %
#335000
0"
b101001111 %
#336000
1"
b101010000 %
#337000
0"
b101010001 %
#338000
1"
b101010010 %
#339000
0"
b101010011 %
#340000
1"
b101010100 %
#341000
0"
b101010101 %
#342000
1"
b101010110 %
#343000
0"
b101010111 %
#344000
1"
b101011000 %
#345000
0"
b101011001 %
#346000
1"
b101011010 %
#347000
0"
b101011011 %
#348000
1"
b101011100 %
#349000
0"
b101011101 %
#350000
1"
b101011110 %
#351000
0"
b101011111 %
#352000
1"
b101100000 %
#353000
0"
b101100001 %
#354000
1"
b101100010 %
#355000
0"
b101100011 %
#356000
1"
b101100100 %
#357000
0"
b101100101 %
#358000
1"
b101100110 %
#359000
0"
b101100111 %
#360000
1"
b101101000 %
#361000
0"
b101101001 %
#362000
1"
b101101010 %
#363000
0"
b101101011 %
#364000
1"
b101101100 %
#365000
0"
b101101101 %
#366000
1"
b101101110 %
#367000
0"
b101101111 %
#368000
1"
b101110000 %
#369000
0"
b101110001 %
#370000
1"
b101110010 %
#371000
0"
b101110011 %
#372000
1"
b101110100 %
#373000
0"
b101110101 %
#374000
1"
b101110110 %
#375000
0"
b101110111 %
#376000
1"
b101111000 %
#377000
0"
b101111001 %
#378000
1"
b101111010 %
#379000
0"
b101111011 %
#380000
1"
b101111100 %
#381000
0"
b101111101 %
#382000
1"
b101111110 %
#383000
0"
b101111111 %
#384000
1"
b110000000 %
#385000
0"
b110000001 %
#386000
1"
b110000010 %
#387000
0"
b110000011 %
#388000
1"
b110000100 %
#389000
0"
b110000101 %
#390000
1"
b110000110 %
#391000
0"
b110000111 %
#392000
1"
b110001000 %
#393000
0"
b110001001 %
#394000
1"
b110001010 %
#395000
0"
b110001011 %
#396000
1"
b110001100 %
#397000
0"
b110001101 %
#398000
1"
b110001110 %
#399000
0"
b110001111 %
#400000
1"
b110010000 %
#401000
0"
b110010001 %
1#
#402000
b0 '
0(
0!
0&
1"
b110010010 %
#403000
0"
b110010011 %
#404000
1"
b110010100 %
#405000
0"
b110010101 %
#406000
1"
b110010110 %
#407000
0"
b110010111 %
#408000
1"
b110011000 %
#409000
0"
b110011001 %
#410000
1"
b110011010 %
#411000
0"
b110011011 %
#412000
b1 '
1"
b110011100 %
0#
#413000
0"
b110011101 %
#414000
b11 '
1"
b110011110 %
#415000
0"
b110011111 %
#416000
b111 '
1"
b110100000 %
#417000
0"
b110100001 %
#418000
b1111 '
1"
b110100010 %
#419000
0"
b110100011 %
#420000
b11111 '
1"
b110100100 %
#421000
0"
b110100101 %
#422000
b111111 '
1"
b110100110 %
#423000
0"
b110100111 %
#424000
b1111111 '
1"
b110101000 %
#425000
0"
b110101001 %
#426000
b11111111 '
1"
b110101010 %
#427000
0"
b110101011 %
#428000
b111111111 '
1"
b110101100 %
#429000
0"
b110101101 %
#430000
b1111111111 '
1"
b110101110 %
#431000
0"
b110101111 %
#432000
b11111111111 '
1"
b110110000 %
#433000
0"
b110110001 %
#434000
b111111111111 '
1"
b110110010 %
#435000
0"
b110110011 %
#436000
b1111111111111 '
1"
b110110100 %
#437000
0"
b110110101 %
#438000
b11111111111111 '
1"
b110110110 %
#439000
0"
b110110111 %
#440000
b111111111111111 '
1"
b110111000 %
#441000
0"
b110111001 %
#442000
b1111111111111111 '
1"
b110111010 %
#443000
0"
b110111011 %
#444000
b11111111111111111 '
1"
b110111100 %
#445000
0"
b110111101 %
#446000
b111111111111111111 '
1"
b110111110 %
#447000
0"
b110111111 %
#448000
b1111111111111111111 '
1"
b111000000 %
#449000
0"
b111000001 %
#450000
b11111111111111111111 '
1"
b111000010 %
#451000
0"
b111000011 %
#452000
b111111111111111111111 '
1"
b111000100 %
#453000
0"
b111000101 %
#454000
b1111111111111111111111 '
1"
b111000110 %
#455000
0"
b111000111 %
#456000
b11111111111111111111111 '
1"
b111001000 %
#457000
0"
b111001001 %
#458000
b111111111111111111111111 '
1"
b111001010 %
#459000
0"
b111001011 %
#460000
b1111111111111111111111111 '
1"
b111001100 %
#461000
0"
b111001101 %
#462000
b11111111111111111111111111 '
1"
b111001110 %
#463000
0"
b111001111 %
#464000
b111111111111111111111111111 '
1"
b111010000 %
#465000
0"
b111010001 %
#466000
b1111111111111111111111111111 '
1"
b111010010 %
#467000
0"
b111010011 %
#468000
b11111111111111111111111111111 '
1"
b111010100 %
#469000
0"
b111010101 %
#470000
b111111111111111111111111111111 '
1"
b111010110 %
#471000
0"
b111010111 %
#472000
b1111111111111111111111111111111 '
1"
b111011000 %
#473000
0"
b111011001 %
#474000
b11111111111111111111111111111111 '
1"
b111011010 %
#475000
0"
b111011011 %
#476000
b111111111111111111111111111111111 '
1"
b111011100 %
#477000
0"
b111011101 %
#478000
b1111111111111111111111111111111111 '
1"
b111011110 %
#479000
0"
b111011111 %
#480000
b11111111111111111111111111111111111 '
1"
b111100000 %
#481000
0"
b111100001 %
#482000
b111111111111111111111111111111111111 '
1"
b111100010 %
#483000
0"
b111100011 %
#484000
b1111111111111111111111111111111111111 '
1"
b111100100 %
#485000
0"
b111100101 %
#486000
b11111111111111111111111111111111111111 '
1"
b111100110 %
#487000
0"
b111100111 %
#488000
b111111111111111111111111111111111111111 '
1"
b111101000 %
#489000
0"
b111101001 %
#490000
b1111111111111111111111111111111111111111 '
1"
b111101010 %
#491000
0"
b111101011 %
#492000
b11111111111111111111111111111111111111111 '
1"
b111101100 %
#493000
0"
b111101101 %
#494000
b111111111111111111111111111111111111111111 '
1"
b111101110 %
#495000
0"
b111101111 %
#496000
b1111111111111111111111111111111111111111111 '
1"
b111110000 %
#497000
0"
b111110001 %
#498000
b11111111111111111111111111111111111111111111 '
1"
b111110010 %
#499000
0"
b111110011 %
#500000
b111111111111111111111111111111111111111111111 '
1"
b111110100 %
#501000
0"
b111110101 %
#502000
b1111111111111111111111111111111111111111111111 '
1"
b111110110 %
#503000
0"
b111110111 %
#504000
b11111111111111111111111111111111111111111111111 '
1"
b111111000 %
#505000
0"
b111111001 %
#506000
b111111111111111111111111111111111111111111111111 '
1"
b111111010 %
#507000
0"
b111111011 %
#508000
b1111111111111111111111111111111111111111111111111 '
1"
b111111100 %
#509000
0"
b111111101 %
#510000
b11111111111111111111111111111111111111111111111111 '
1"
b111111110 %
#511000
0"
b111111111 %
#512000
b111111111111111111111111111111111111111111111111111 '
1"
b1000000000 %
#513000
0"
b1000000001 %
#514000
b1111111111111111111111111111111111111111111111111111 '
1"
b1000000010 %
#515000
0"
b1000000011 %
#516000
b11111111111111111111111111111111111111111111111111111 '
1"
b1000000100 %
#517000
0"
b1000000101 %
#518000
b111111111111111111111111111111111111111111111111111111 '
1"
b1000000110 %
#519000
0"
b1000000111 %
#520000
b1111111111111111111111111111111111111111111111111111111 '
1"
b1000001000 %
#521000
0"
b1000001001 %
#522000
b11111111111111111111111111111111111111111111111111111111 '
1"
b1000001010 %
#523000
0"
b1000001011 %
#524000
b111111111111111111111111111111111111111111111111111111111 '
1"
b1000001100 %
#525000
0"
b1000001101 %
#526000
b1111111111111111111111111111111111111111111111111111111111 '
1"
b1000001110 %
#527000
0"
b1000001111 %
#528000
b11111111111111111111111111111111111111111111111111111111111 '
1"
b1000010000 %
#529000
0"
b1000010001 %
#530000
b111111111111111111111111111111111111111111111111111111111111 '
1"
b1000010010 %
#531000
0"
b1000010011 %
#532000
b1111111111111111111111111111111111111111111111111111111111111 '
1"
b1000010100 %
#533000
0"
b1000010101 %
#534000
b11111111111111111111111111111111111111111111111111111111111111 '
1"
b1000010110 %
#535000
0"
b1000010111 %
#536000
b111111111111111111111111111111111111111111111111111111111111111 '
1"
b1000011000 %
#537000
0"
b1000011001 %
#538000
b1111111111111111111111111111111111111111111111111111111111111111 '
1"
b1000011010 %
#539000
0"
b1000011011 %
#540000
b11111111111111111111111111111111111111111111111111111111111111111 '
1"
b1000011100 %
#541000
0"
b1000011101 %
#542000
b111111111111111111111111111111111111111111111111111111111111111111 '
1"
b1000011110 %
#543000
0"
b1000011111 %
#544000
b1111111111111111111111111111111111111111111111111111111111111111111 '
1"
b1000100000 %
#545000
0"
b1000100001 %
#546000
b11111111111111111111111111111111111111111111111111111111111111111111 '
1"
b1000100010 %
#547000
0"
b1000100011 %
#548000
b111111111111111111111111111111111111111111111111111111111111111111111 '
1"
b1000100100 %
#549000
0"
b1000100101 %
#550000
b1111111111111111111111111111111111111111111111111111111111111111111111 '
1"
b1000100110 %
#551000
0"
b1000100111 %
#552000
b11111111111111111111111111111111111111111111111111111111111111111111111 '
1"
b1000101000 %
#553000
0"
b1000101001 %
#554000
b111111111111111111111111111111111111111111111111111111111111111111111111 '
1"
b1000101010 %
#555000
0"
b1000101011 %
#556000
b1111111111111111111111111111111111111111111111111111111111111111111111111 '
1"
b1000101100 %
#557000
0"
b1000101101 %
#558000
b11111111111111111111111111111111111111111111111111111111111111111111111111 '
1"
b1000101110 %
#559000
0"
b1000101111 %
#560000
b111111111111111111111111111111111111111111111111111111111111111111111111111 '
1"
b1000110000 %
#561000
0"
b1000110001 %
#562000
b1111111111111111111111111111111111111111111111111111111111111111111111111111 '
1"
b1000110010 %
#563000
0"
b1000110011 %
#564000
b11111111111111111111111111111111111111111111111111111111111111111111111111111 '
1"
b1000110100 %
#565000
0"
b1000110101 %
#566000
b111111111111111111111111111111111111111111111111111111111111111111111111111111 '
1"
b1000110110 %
#567000
0"
b1000110111 %
#568000
b1111111111111111111111111111111111111111111111111111111111111111111111111111111 '
1"
b1000111000 %
#569000
0"
b1000111001 %
#570000
b11111111111111111111111111111111111111111111111111111111111111111111111111111111 '
1"
b1000111010 %
#571000
0"
b1000111011 %
#572000
b111111111111111111111111111111111111111111111111111111111111111111111111111111111 '
1"
b1000111100 %
#573000
0"
b1000111101 %
#574000
b1111111111111111111111111111111111111111111111111111111111111111111111111111111111 '
1"
b1000111110 %
#575000
0"
b1000111111 %
#576000
b11111111111111111111111111111111111111111111111111111111111111111111111111111111111 '
1"
b1001000000 %
#577000
0"
b1001000001 %
#578000
b111111111111111111111111111111111111111111111111111111111111111111111111111111111111 '
1"
b1001000010 %
#579000
0"
b1001000011 %
#580000
b1111111111111111111111111111111111111111111111111111111111111111111111111111111111111 '
1"
b1001000100 %
#581000
0"
b1001000101 %
#582000
b11111111111111111111111111111111111111111111111111111111111111111111111111111111111111 '
1"
b1001000110 %
#583000
0"
b1001000111 %
#584000
b111111111111111111111111111111111111111111111111111111111111111111111111111111111111111 '
1"
b1001001000 %
#585000
0"
b1001001001 %
#586000
b1111111111111111111111111111111111111111111111111111111111111111111111111111111111111111 '
1"
b1001001010 %
#587000
0"
b1001001011 %
#588000
b11111111111111111111111111111111111111111111111111111111111111111111111111111111111111111 '
1"
b1001001100 %
#589000
0"
b1001001101 %
#590000
b111111111111111111111111111111111111111111111111111111111111111111111111111111111111111111 '
1"
b1001001110 %
#591000
0"
b1001001111 %
#592000
b1111111111111111111111111111111111111111111111111111111111111111111111111111111111111111111 '
1"
b1001010000 %
#593000
0"
b1001010001 %
#594000
b11111111111111111111111111111111111111111111111111111111111111111111111111111111111111111111 '
1"
b1001010010 %
#595000
0"
b1001010011 %
#596000
b111111111111111111111111111111111111111111111111111111111111111111111111111111111111111111111 '
1"
b1001010100 %
#597000
0"
b1001010101 %
#598000
b1111111111111111111111111111111111111111111111111111111111111111111111111111111111111111111111 '
1"
b1001010110 %
#599000
0"
b1001010111 %
#600000
b11111111111111111111111111111111111111111111111111111111111111111111111111111111111111111111111 '
1"
b1001011000 %
#601000
0"
b1001011001 %
#602000
b111111111111111111111111111111111111111111111111111111111111111111111111111111111111111111111111 '
1"
b1001011010 %
#603000
0"
b1001011011 %
#604000
b1111111111111111111111111111111111111111111111111111111111111111111111111111111111111111111111111 '
1"
b1001011100 %
#605000
0"
b1001011101 %
#606000
b11111111111111111111111111111111111111111111111111111111111111111111111111111111111111111111111111 '
1"
b1001011110 %
#607000
0"
b1001011111 %
#608000
b111111111111111111111111111111111111111111111111111111111111111111111111111111111111111111111111111 '
1"
b1001100000 %
#609000
0"
b1001100001 %
#610000
b1111111111111111111111111111111111111111111111111111111111111111111111111111111111111111111111111111 '
1"
b1001100010 %
#611000
0"
b1001100011 %
#612000
b11111111111111111111111111111111111111111111111111111111111111111111111111111111111111111111111111111 '
1"
b1001100100 %
#613000
0"
b1001100101 %
#614000
b111111111111111111111111111111111111111111111111111111111111111111111111111111111111111111111111111111 '
1"
b1001100110 %
#615000
0"
b1001100111 %
#616000
b1111111111111111111111111111111111111111111111111111111111111111111111111111111111111111111111111111111 '
1"
b1001101000 %
#617000
0"
b1001101001 %
#618000
b11111111111111111111111111111111111111111111111111111111111111111111111111111111111111111111111111111111 '
1"
b1001101010 %
#619000
0"
b1001101011 %
#620000
b111111111111111111111111111111111111111111111111111111111111111111111111111111111111111111111111111111111 '
1"
b1001101100 %
#621000
0"
b1001101101 %
#622000
b1111111111111111111111111111111111111111111111111111111111111111111111111111111111111111111111111111111111 '
1"
b1001101110 %
#623000
0"
b1001101111 %
#624000
b11111111111111111111111111111111111111111111111111111111111111111111111111111111111111111111111111111111111 '
1"
b1001110000 %
#625000
0"
b1001110001 %
#626000
b111111111111111111111111111111111111111111111111111111111111111111111111111111111111111111111111111111111111 '
1"
b1001110010 %
#627000
0"
b1001110011 %
#628000
b1111111111111111111111111111111111111111111111111111111111111111111111111111111111111111111111111111111111111 '
1"
b1001110100 %
#629000
0"
b1001110101 %
#630000
b11111111111111111111111111111111111111111111111111111111111111111111111111111111111111111111111111111111111111 '
1"
b1001110110 %
#631000
0"
b1001110111 %
#632000
b111111111111111111111111111111111111111111111111111111111111111111111111111111111111111111111111111111111111111 '
1"
b1001111000 %
#633000
0"
b1001111001 %
#634000
b1111111111111111111111111111111111111111111111111111111111111111111111111111111111111111111111111111111111111111 '
1"
b1001111010 %
#635000
0"
b1001111011 %
#636000
b11111111111111111111111111111111111111111111111111111111111111111111111111111111111111111111111111111111111111111 '
1"
b1001111100 %
#637000
0"
b1001111101 %
#638000
b111111111111111111111111111111111111111111111111111111111111111111111111111111111111111111111111111111111111111111 '
1"
b1001111110 %
#639000
0"
b1001111111 %
#640000
b1111111111111111111111111111111111111111111111111111111111111111111111111111111111111111111111111111111111111111111 '
1"
b1010000000 %
#641000
0"
b1010000001 %
#642000
b11111111111111111111111111111111111111111111111111111111111111111111111111111111111111111111111111111111111111111111 '
1"
b1010000010 %
#643000
0"
b1010000011 %
#644000
b111111111111111111111111111111111111111111111111111111111111111111111111111111111111111111111111111111111111111111111 '
1"
b1010000100 %
#645000
0"
b1010000101 %
#646000
b1111111111111111111111111111111111111111111111111111111111111111111111111111111111111111111111111111111111111111111111 '
1"
b1010000110 %
#647000
0"
b1010000111 %
#648000
b11111111111111111111111111111111111111111111111111111111111111111111111111111111111111111111111111111111111111111111111 '
1"
b1010001000 %
#649000
0"
b1010001001 %
#650000
b111111111111111111111111111111111111111111111111111111111111111111111111111111111111111111111111111111111111111111111111 '
1"
b1010001010 %
#651000
0"
b1010001011 %
#652000
b1111111111111111111111111111111111111111111111111111111111111111111111111111111111111111111111111111111111111111111111111 '
1"
b1010001100 %
#653000
0"
b1010001101 %
#654000
b11111111111111111111111111111111111111111111111111111111111111111111111111111111111111111111111111111111111111111111111111 '
1"
b1010001110 %
#655000
0"
b1010001111 %
#656000
b111111111111111111111111111111111111111111111111111111111111111111111111111111111111111111111111111111111111111111111111111 '
1"
b1010010000 %
#657000
0"
b1010010001 %
#658000
b1111111111111111111111111111111111111111111111111111111111111111111111111111111111111111111111111111111111111111111111111111 '
1"
b1010010010 %
#659000
0"
b1010010011 %
#660000
b11111111111111111111111111111111111111111111111111111111111111111111111111111111111111111111111111111111111111111111111111111 '
1"
b1010010100 %
#661000
0"
b1010010101 %
#662000
b111111111111111111111111111111111111111111111111111111111111111111111111111111111111111111111111111111111111111111111111111111 '
1"
b1010010110 %
#663000
0"
b1010010111 %
#664000
b1111111111111111111111111111111111111111111111111111111111111111111111111111111111111111111111111111111111111111111111111111111 '
1"
b1010011000 %
#665000
0"
b1010011001 %
#666000
b11111111111111111111111111111111111111111111111111111111111111111111111111111111111111111111111111111111111111111111111111111111 '
1"
b1010011010 %
#667000
0"
b1010011011 %
#668000
b111111111111111111111111111111111111111111111111111111111111111111111111111111111111111111111111111111111111111111111111111111111 '
1"
b1010011100 %
#669000
0"
b1010011101 %
#670000
b1111111111111111111111111111111111111111111111111111111111111111111111111111111111111111111111111111111111111111111111111111111111 '
1"
b1010011110 %
#671000
0"
b1010011111 %
#672000
b11111111111111111111111111111111111111111111111111111111111111111111111111111111111111111111111111111111111111111111111111111111111 '
1"
b1010100000 %
#673000
0"
b1010100001 %
#674000
b111111111111111111111111111111111111111111111111111111111111111111111111111111111111111111111111111111111111111111111111111111111111 '
1"
b1010100010 %
#675000
0"
b1010100011 %
#676000
b1111111111111111111111111111111111111111111111111111111111111111111111111111111111111111111111111111111111111111111111111111111111111 '
1"
b1010100100 %
#677000
0"
b1010100101 %
#678000
b11111111111111111111111111111111111111111111111111111111111111111111111111111111111111111111111111111111111111111111111111111111111111 '
1"
b1010100110 %
#679000
0"
b1010100111 %
#680000
b111111111111111111111111111111111111111111111111111111111111111111111111111111111111111111111111111111111111111111111111111111111111111 '
1"
b1010101000 %
#681000
0"
b1010101001 %
#682000
b1111111111111111111111111111111111111111111111111111111111111111111111111111111111111111111111111111111111111111111111111111111111111111 '
1"
b1010101010 %
#683000
0"
b1010101011 %
#684000
b11111111111111111111111111111111111111111111111111111111111111111111111111111111111111111111111111111111111111111111111111111111111111111 '
1"
b1010101100 %
#685000
0"
b1010101101 %
#686000
b111111111111111111111111111111111111111111111111111111111111111111111111111111111111111111111111111111111111111111111111111111111111111111 '
1"
b1010101110 %
#687000
0"
b1010101111 %
#688000
b1111111111111111111111111111111111111111111111111111111111111111111111111111111111111111111111111111111111111111111111111111111111111111111 '
1"
b1010110000 %
#689000
0"
b1010110001 %
#690000
b11111111111111111111111111111111111111111111111111111111111111111111111111111111111111111111111111111111111111111111111111111111111111111111 '
1"
b1010110010 %
#691000
0"
b1010110011 %
#692000
b111111111111111111111111111111111111111111111111111111111111111111111111111111111111111111111111111111111111111111111111111111111111111111111 '
1"
b1010110100 %
#693000
0"
b1010110101 %
#694000
b1111111111111111111111111111111111111111111111111111111111111111111111111111111111111111111111111111111111111111111111111111111111111111111111 '
1"
b1010110110 %
#695000
0"
b1010110111 %
#696000
b11111111111111111111111111111111111111111111111111111111111111111111111111111111111111111111111111111111111111111111111111111111111111111111111 '
1"
b1010111000 %
#697000
0"
b1010111001 %
#698000
b111111111111111111111111111111111111111111111111111111111111111111111111111111111111111111111111111111111111111111111111111111111111111111111111 '
1"
b1010111010 %
