project3/rootfunction/sqrt.sv
module sqrt(input RESET, PREVIOUS, NEXT,CLK, input [31:0] N , input [31:0] DELTA , output reg [63:0] m);
//input [31:0] H, input [31:0] L , input [31:0] N , input [31:0] DELTA , output reg [63:0] m);

    //internal 

    reg done;    
    
    
    reg [31:0] sqrt;
    reg [31:0] h;
    reg [31:0] l;
    reg [31:0] n;
    reg [31:0] delta;
    reg [4:0]  iterations;
    reg [63:0] current_sqrt;
    //reg [63:0] m;
    always @(posedge CLK) begin
        
        // apply variables initialize when PREVIOUS and NEXT are both 1
        if(PREVIOUS && NEXT) begin
         
            n = N;
            delta = DELTA;    
            iterations = 0;
            done = 0;
            sqrt = n;
            
        end
        
        if(~done) begin
        
        current_sqrt = (h + l)/2;
        
        //begin logic
        if(delta >= 2*(-16)) begin
            
            if(current_sqrt * current_sqrt > n) begin
                        
                    h = current_sqrt;
                    n = N; 
                    delta = delta / 2;
            
            end else begin
                    
                    l = current_sqrt;
                    n = N; 
                    delta = delta / 2;    
                    
            end
      
        end
        
        
        //stops after 16 iterations
        if(iterations == 17) begin
  
            done = 1;
            iterations = 0;
            
        end
        
         //reset signal
        if(RESET) begin
            
            sqrt = 1;
            done = 1;
            delta = 1;
            current_sqrt = 1;
        
        end
             if(NEXT) begin
            
             h = sqrt + delta;
             l = sqrt;
             n = n+1;
             delta = delta;
             sqrt = (n+1);
             
        end
        
        if(PREVIOUS) begin
            
            h = sqrt;
            l = sqrt - delta;
            n = n - 1;
            delta = delta;
            
            sqrt = (n-1);
        
        end
         m = current_sqrt; 
            
         iterations = iterations +1; 
         
       end
              
    end

endmodule

System_Verilog_code_base/rootfunction/printsqrt.sv
module printsqrt (input RESET, PREVIOUS, NEXT,CLK, input [31:0] N , input [31:0] DELTA ,input [31:0] i);

    wire [63:0] m;
    
    sqrt math(RESET, PREVIOUS, NEXT, CLK, N, DELTA ,m);

    always @(posedge CLK) begin
   
    if(i < 200) begin
    
        $display("m = %f", m);
        
        end
    end
    
endmodule

System_Verilog_code_base/rootfunction/sqrt_tb.sv
`timescale 1ns/10ps

module squrt_tb;

    reg clk,reset,next,previous;
    reg [31:0] n;
    reg [31:0] delta;
    
    integer i ;
    
    
    initial begin
        
        clk = 0;
        n = 1'd1;
        delta = 3'b00_1;
    
        reset = 0;
        next = 1;
        previous = 1;
    
        $dumpfile("sqrt_tb.vcd");
        $dumpvars;
        
        for(i = 0; i < 200 ; i = i+1) begin
            clk = ~clk; #10;
            
            if(i > 1)begin
                previous = 0;
            end
           
           /*  
            if( i >= 30 ) begin
                
                
                reset = 1;
                
               end
           
            if( i > 39 && i < 45) begin
                next = 1;
                previous = 1;
               end
            
            if(i > 50) begin
          
                next = 0;
                previous =1;
            
            end*/
            
        end
      
    end
    
    printsqrt print(reset,previous,next,clk,n,delta,i);
    

endmodule

project3/rootfunction/sqrt_tb.vcd
$date
	Thu Feb 10 19:40:09 2022
$end
$version
	Icarus Verilog
$end
$timescale
	10ps
$end
$scope module squrt_tb $end
$var reg 1 ! clk $end
$var reg 32 " delta [31:0] $end
$var reg 32 # n [31:0] $end
$var reg 1 $ next $end
$var reg 1 % previous $end
$var reg 1 & reset $end
$var integer 32 ' i [31:0] $end
$scope module print $end
$var wire 1 ! CLK $end
$var wire 32 ( DELTA [31:0] $end
$var wire 32 ) N [31:0] $end
$var wire 1 $ NEXT $end
$var wire 1 % PREVIOUS $end
$var wire 1 & RESET $end
$var wire 32 * i [31:0] $end
$var wire 64 + m [63:0] $end
$scope module math $end
$var wire 1 ! CLK $end
$var wire 32 , DELTA [31:0] $end
$var wire 32 - N [31:0] $end
$var wire 1 $ NEXT $end
$var wire 1 % PREVIOUS $end
$var wire 1 & RESET $end
$var reg 64 . current_sqrt [63:0] $end
$var reg 32 / delta [31:0] $end
$var reg 1 0 done $end
$var reg 32 1 h [31:0] $end
$var reg 5 2 iterations [4:0] $end
$var reg 32 3 l [31:0] $end
$var reg 64 4 m [63:0] $end
$var reg 32 5 n [31:0] $end
$var reg 32 6 sqrt [31:0] $end
$upscope $end
$upscope $end
$upscope $end
$enddefinitions $end
#0
$dumpvars
b0 6
b1 5
bx 4
b10 3
b1 2
b11 1
00
b1 /
bx .
b1 -
b1 ,
bx +
b0 *
b1 )
b1 (
b0 '
0&
1%
1$
b1 #
b1 "
1!
$end
#1000
0!
b1 '
b1 *
#2000
b10 +
b10 4
b1 5
b10 3
b11 1
b10 .
b0 6
b1 2
1!
b10 '
b10 *
#3000
0!
b11 '
b11 *
0%
#4000
b10 2
b11 6
b10 5
b0 3
b1 1
1!
b100 '
b100 *
#5000
0!
b101 '
b101 *
#6000
b11 2
b0 +
b0 4
b100 6
b11 5
b11 3
b100 1
b0 .
1!
b110 '
b110 *
#7000
0!
b111 '
b111 *
#8000
b100 2
b11 +
b11 4
b101 6
b100 5
b100 3
b101 1
b11 .
1!
b1000 '
b1000 *
#9000
0!
b1001 '
b1001 *
#10000
b101 2
b100 +
b100 4
b110 6
b101 5
b101 3
b110 1
b100 .
1!
b1010 '
b1010 *
#11000
0!
b1011 '
b1011 *
#12000
b110 2
b101 +
b101 4
b111 6
b110 5
b110 3
b111 1
b101 .
1!
b1100 '
b1100 *
#13000
0!
b1101 '
b1101 *
#14000
b111 2
b110 +
b110 4
b1000 6
b111 5
b111 3
b1000 1
b110 .
1!
b1110 '
b1110 *
#15000
0!
b1111 '
b1111 *
#16000
b1000 2
b111 +
b111 4
b1001 6
b1000 5
b1000 3
b1001 1
b111 .
1!
b10000 '
b10000 *
#17000
0!
b10001 '
b10001 *
#18000
b1001 2
b1000 +
b1000 4
b1010 6
b1001 5
b1001 3
b1010 1
b1000 .
1!
b10010 '
b10010 *
#19000
0!
b10011 '
b10011 *
#20000
b1010 2
b1001 +
b1001 4
b1011 6
b1010 5
b1010 3
b1011 1
b1001 .
1!
b10100 '
b10100 *
#21000
0!
b10101 '
b10101 *
#22000
b1011 2
b1010 +
b1010 4
b1100 6
b1011 5
b1011 3
b1100 1
b1010 .
1!
b10110 '
b10110 *
#23000
0!
b10111 '
b10111 *
#24000
b1100 2
b1011 +
b1011 4
b1101 6
b1100 5
b1100 3
b1101 1
b1011 .
1!
b11000 '
b11000 *
#25000
0!
b11001 '
b11001 *
#26000
b1101 2
b1100 +
b1100 4
b1110 6
b1101 5
b1101 3
b1110 1
b1100 .
1!
b11010 '
b11010 *
#27000
0!
b11011 '
b11011 *
#28000
b1110 2
b1101 +
b1101 4
b1111 6
b1110 5
b1110 3
b1111 1
b1101 .
1!
b11100 '
b11100 *
#29000
0!
b11101 '
b11101 *
#30000
b1111 2
b1110 +
b1110 4
b10000 6
b1111 5
b1111 3
b10000 1
b1110 .
1!
b11110 '
b11110 *
#31000
0!
b11111 '
b11111 *
#32000
b10000 2
b1111 +
b1111 4
b10001 6
b10000 5
b10000 3
b10001 1
b1111 .
1!
b100000 '
b100000 *
#33000
0!
b100001 '
b100001 *
#34000
b10001 2
b10000 +
b10000 4
b10010 6
b10001 5
b10001 3
b10010 1
b10000 .
1!
b100010 '
b100010 *
#35000
0!
b100011 '
b100011 *
#36000
b10001 +
b10001 4
b10011 6
b10010 5
b10010 3
b10011 1
b1 2
10
b10001 .
1!
b100100 '
b100100 *
#37000
0!
b100101 '
b100101 *
#38000
1!
b100110 '
b100110 *
#39000
0!
b100111 '
b100111 *
#40000
1!
b101000 '
b101000 *
#41000
0!
b101001 '
b101001 *
#42000
1!
b101010 '
b101010 *
#43000
0!
b101011 '
b101011 *
#44000
1!
b101100 '
b101100 *
#45000
0!
b101101 '
b101101 *
#46000
1!
b101110 '
b101110 *
#47000
0!
b101111 '
b101111 *
#48000
1!
b110000 '
b110000 *
#49000
0!
b110001 '
b110001 *
#50000
1!
b110010 '
b110010 *
#51000
0!
b110011 '
b110011 *
#52000
1!
b110100 '
b110100 *
#53000
0!
b110101 '
b110101 *
#54000
1!
b110110 '
b110110 *
#55000
0!
b110111 '
b110111 *
#56000
1!
b111000 '
b111000 *
#57000
0!
b111001 '
b111001 *
#58000
1!
b111010 '
b111010 *
#59000
0!
b111011 '
b111011 *
#60000
1!
b111100 '
b111100 *
#61000
0!
b111101 '
b111101 *
#62000
1!
b111110 '
b111110 *
#63000
0!
b111111 '
b111111 *
#64000
1!
b1000000 '
b1000000 *
#65000
0!
b1000001 '
b1000001 *
#66000
1!
b1000010 '
b1000010 *
#67000
0!
b1000011 '
b1000011 *
#68000
1!
b1000100 '
b1000100 *
#69000
0!
b1000101 '
b1000101 *
#70000
1!
b1000110 '
b1000110 *
#71000
0!
b1000111 '
b1000111 *
#72000
1!
b1001000 '
b1001000 *
#73000
0!
b1001001 '
b1001001 *
#74000
1!
b1001010 '
b1001010 *
#75000
0!
b1001011 '
b1001011 *
#76000
1!
b1001100 '
b1001100 *
#77000
0!
b1001101 '
b1001101 *
#78000
1!
b1001110 '
b1001110 *
#79000
0!
b1001111 '
b1001111 *
#80000
1!
b1010000 '
b1010000 *
#81000
0!
b1010001 '
b1010001 *
#82000
1!
b1010010 '
b1010010 *
#83000
0!
b1010011 '
b1010011 *
#84000
1!
b1010100 '
b1010100 *
#85000
0!
b1010101 '
b1010101 *
#86000
1!
b1010110 '
b1010110 *
#87000
0!
b1010111 '
b1010111 *
#88000
1!
b1011000 '
b1011000 *
#89000
0!
b1011001 '
b1011001 *
#90000
1!
b1011010 '
b1011010 *
#91000
0!
b1011011 '
b1011011 *
#92000
1!
b1011100 '
b1011100 *
#93000
0!
b1011101 '
b1011101 *
#94000
1!
b1011110 '
b1011110 *
#95000
0!
b1011111 '
b1011111 *
#96000
1!
b1100000 '
b1100000 *
#97000
0!
b1100001 '
b1100001 *
#98000
1!
b1100010 '
b1100010 *
#99000
0!
b1100011 '
b1100011 *
#100000
1!
b1100100 '
b1100100 *
#101000
0!
b1100101 '
b1100101 *
#102000
1!
b1100110 '
b1100110 *
#103000
0!
b1100111 '
b1100111 *
#104000
1!
b1101000 '
b1101000 *
#105000
0!
b1101001 '
b1101001 *
#106000
1!
b1101010 '
b1101010 *
#107000
0!
b1101011 '
b1101011 *
#108000
1!
b1101100 '
b1101100 *
#109000
0!
b1101101 '
b1101101 *
#110000
1!
b1101110 '
b1101110 *
#111000
0!
b1101111 '
b1101111 *
#112000
1!
b1110000 '
b1110000 *
#113000
0!
b1110001 '
b1110001 *
#114000
1!
b1110010 '
b1110010 *
#115000
0!
b1110011 '
b1110011 *
#116000
1!
b1110100 '
b1110100 *
#117000
0!
b1110101 '
b1110101 *
#118000
1!
b1110110 '
b1110110 *
#119000
0!
b1110111 '
b1110111 *
#120000
1!
b1111000 '
b1111000 *
#121000
0!
b1111001 '
b1111001 *
#122000
1!
b1111010 '
b1111010 *
#123000
0!
b1111011 '
b1111011 *
#124000
1!
b1111100 '
b1111100 *
#125000
0!
b1111101 '
b1111101 *
#126000
1!
b1111110 '
b1111110 *
#127000
0!
b1111111 '
b1111111 *
#128000
1!
b10000000 '
b10000000 *
#129000
0!
b10000001 '
b10000001 *
#130000
1!
b10000010 '
b10000010 *
#131000
0!
b10000011 '
b10000011 *
#132000
1!
b10000100 '
b10000100 *
#133000
0!
b10000101 '
b10000101 *
#134000
1!
b10000110 '
b10000110 *
#135000
0!
b10000111 '
b10000111 *
#136000
1!
b10001000 '
b10001000 *
#137000
0!
b10001001 '
b10001001 *
#138000
1!
b10001010 '
b10001010 *
#139000
0!
b10001011 '
b10001011 *
#140000
1!
b10001100 '
b10001100 *
#141000
0!
b10001101 '
b10001101 *
#142000
1!
b10001110 '
b10001110 *
#143000
0!
b10001111 '
b10001111 *
#144000
1!
b10010000 '
b10010000 *
#145000
0!
b10010001 '
b10010001 *
#146000
1!
b10010010 '
b10010010 *
#147000
0!
b10010011 '
b10010011 *
#148000
1!
b10010100 '
b10010100 *
#149000
0!
b10010101 '
b10010101 *
#150000
1!
b10010110 '
b10010110 *
#151000
0!
b10010111 '
b10010111 *
#152000
1!
b10011000 '
b10011000 *
#153000
0!
b10011001 '
b10011001 *
#154000
1!
b10011010 '
b10011010 *
#155000
0!
b10011011 '
b10011011 *
#156000
1!
b10011100 '
b10011100 *
#157000
0!
b10011101 '
b10011101 *
#158000
1!
b10011110 '
b10011110 *
#159000
0!
b10011111 '
b10011111 *
#160000
1!
b10100000 '
b10100000 *
#161000
0!
b10100001 '
b10100001 *
#162000
1!
b10100010 '
b10100010 *
#163000
0!
b10100011 '
b10100011 *
#164000
1!
b10100100 '
b10100100 *
#165000
0!
b10100101 '
b10100101 *
#166000
1!
b10100110 '
b10100110 *
#167000
0!
b10100111 '
b10100111 *
#168000
1!
b10101000 '
b10101000 *
#169000
0!
b10101001 '
b10101001 *
#170000
1!
b10101010 '
b10101010 *
#171000
0!
b10101011 '
b10101011 *
#172000
1!
b10101100 '
b10101100 *
#173000
0!
b10101101 '
b10101101 *
#174000
1!
b10101110 '
b10101110 *
#175000
0!
b10101111 '
b10101111 *
#176000
1!
b10110000 '
b10110000 *
#177000
0!
b10110001 '
b10110001 *
#178000
1!
b10110010 '
b10110010 *
#179000
0!
b10110011 '
b10110011 *
#180000
1!
b10110100 '
b10110100 *
#181000
0!
b10110101 '
b10110101 *
#182000
1!
b10110110 '
b10110110 *
#183000
0!
b10110111 '
b10110111 *
#184000
1!
b10111000 '
b10111000 *
#185000
0!
b10111001 '
b10111001 *
#186000
1!
b10111010 '
b10111010 *
#187000
0!
b10111011 '
b10111011 *
#188000
1!
b10111100 '
b10111100 *
#189000
0!
b10111101 '
b10111101 *
#190000
1!
b10111110 '
b10111110 *
#191000
0!
b10111111 '
b10111111 *
#192000
1!
b11000000 '
b11000000 *
#193000
0!
b11000001 '
b11000001 *
#194000
1!
b11000010 '
b11000010 *
#195000
0!
b11000011 '
b11000011 *
#196000
1!
b11000100 '
b11000100 *
#197000
0!
b11000101 '
b11000101 *
#198000
1!
b11000110 '
b11000110 *
#199000
0!
b11000111 '
b11000111 *
#200000
b11001000 '
b11001000 *
