System_Verilog_code_base/FSM/database.sv
module database(input clk, enable, input [3:0] code, output reg done);

    reg [3:0] ROM[15:0];
    reg [3:0]checksum = 0;

    always @(clk) begin
      
      if(enable)begin
            ROM[0] = 4'b0000;   //wasser
            ROM[1] = 4'b0001;   //cola
            ROM[2] = 4'b0010;   //orange
            ROM[3] = 4'b0011;   //zitrone
            ROM[4] = 4'b0100;   //tee
            ROM[5] = 4'b0101;   //kaffe
            ROM[6] = 4'b0110;   //cappucino
            ROM[7] = 4'b0111;   //latte macchiato
            ROM[8] = 4'b1000;   //wasser mit eis
            ROM[9] = 4'b1001;   //cola mit eis
            ROM[10] = 4'b1010;  //orange mit eis
            ROM[11] = 4'b1011;  //zitrone mit ein
            ROM[12] = 4'b1100;  //tee mit zucker
            ROM[13] = 4'b1101;  //kaffe mit zucker
            ROM[14] = 4'b1110;  //cappucino mit zucker
            ROM[15] = 4'b1111;  //latte macchiato mit zucker
            
            
            if(checksum == 15) begin
                checksum <= 0;
            end 
            else begin
            
                checksum  = checksum + 1;
            end
            
            if(code == ROM[checksum]) done = 1;
            else done  = 0;
                
            
        end
    end

endmodule

project3/FSM/database_tb.sv
`timescale 1ns/10ps

module database_tb;


    reg[3:0] code;
    reg clk;
    integer i ;
    wire out;
    reg enable;
    
    initial begin
    
        clk = 0;
        enable  = 0;
        
        $dumpfile("database_tb.vcd");
        $dumpvars;
        
   
        code = 4'b1110;     
    
    
        for(i = 0 ; i < 100 ; i++)begin
         clk = ~clk; #10;
        end
    
    end
        
        database db( clk,enable,code,out);

endmodule

System_Verilog_code_base/FSM/database_tb.vcd
$date
	Sat Feb 12 21:43:45 2022
$end
$version
	Icarus Verilog
$end
$timescale
	10ps
$end
$scope module database_tb $end
$var wire 1 ! out $end
$var reg 1 " clk $end
$var reg 4 # code [3:0] $end
$var reg 1 $ enable $end
$var integer 32 % i [31:0] $end
$scope module db $end
$var wire 1 " clk $end
$var wire 4 & code [3:0] $end
$var wire 1 $ enable $end
$var reg 4 ' checksum [3:0] $end
$var reg 1 ! done $end
$upscope $end
$upscope $end
$enddefinitions $end
#0
$dumpvars
b0 '
b1110 &
b0 %
0$
b1110 #
1"
x!
$end
#1000
0"
b1 %
#2000
1"
b10 %
#3000
0"
b11 %
#4000
1"
b100 %
#5000
0"
b101 %
#6000
1"
b110 %
#7000
0"
b111 %
#8000
1"
b1000 %
#9000
0"
b1001 %
#10000
1"
b1010 %
#11000
0"
b1011 %
#12000
1"
b1100 %
#13000
0"
b1101 %
#14000
1"
b1110 %
#15000
0"
b1111 %
#16000
1"
b10000 %
#17000
0"
b10001 %
#18000
1"
b10010 %
#19000
0"
b10011 %
#20000
1"
b10100 %
#21000
0"
b10101 %
#22000
1"
b10110 %
#23000
0"
b10111 %
#24000
1"
b11000 %
#25000
0"
b11001 %
#26000
1"
b11010 %
#27000
0"
b11011 %
#28000
1"
b11100 %
#29000
0"
b11101 %
#30000
1"
b11110 %
#31000
0"
b11111 %
#32000
1"
b100000 %
#33000
0"
b100001 %
#34000
1"
b100010 %
#35000
0"
b100011 %
#36000
1"
b100100 %
#37000
0"
b100101 %
#38000
1"
b100110 %
#39000
0"
b100111 %
#40000
1"
b101000 %
#41000
0"
b101001 %
#42000
1"
b101010 %
#43000
0"
b101011 %
#44000
1"
b101100 %
#45000
0"
b101101 %
#46000
1"
b101110 %
#47000
0"
b101111 %
#48000
1"
b110000 %
#49000
0"
b110001 %
#50000
1"
b110010 %
#51000
0"
b110011 %
#52000
1"
b110100 %
#53000
0"
b110101 %
#54000
1"
b110110 %
#55000
0"
b110111 %
#56000
1"
b111000 %
#57000
0"
b111001 %
#58000
1"
b111010 %
#59000
0"
b111011 %
#60000
1"
b111100 %
#61000
0"
b111101 %
#62000
1"
b111110 %
#63000
0"
b111111 %
#64000
1"
b1000000 %
#65000
0"
b1000001 %
#66000
1"
b1000010 %
#67000
0"
b1000011 %
#68000
1"
b1000100 %
#69000
0"
b1000101 %
#70000
1"
b1000110 %
#71000
0"
b1000111 %
#72000
1"
b1001000 %
#73000
0"
b1001001 %
#74000
1"
b1001010 %
#75000
0"
b1001011 %
#76000
1"
b1001100 %
#77000
0"
b1001101 %
#78000
1"
b1001110 %
#79000
0"
b1001111 %
#80000
1"
b1010000 %
#81000
0"
b1010001 %
#82000
1"
b1010010 %
#83000
0"
b1010011 %
#84000
1"
b1010100 %
#85000
0"
b1010101 %
#86000
1"
b1010110 %
#87000
0"
b1010111 %
#88000
1"
b1011000 %
#89000
0"
b1011001 %
#90000
1"
b1011010 %
#91000
0"
b1011011 %
#92000
1"
b1011100 %
#93000
0"
b1011101 %
#94000
1"
b1011110 %
#95000
0"
b1011111 %
#96000
1"
b1100000 %
#97000
0"
b1100001 %
#98000
1"
b1100010 %
#99000
0"
b1100011 %
#100000
b1100100 %
