System_Verilog_code_base/motorcontroler/steppermotor.sv
module steppermotor(input dir,enable,pulse, input wire signed [31:0] distance);



      //coils
reg A,B,C,D;

      //step count
reg [31:0] steps = 0;
      //step position
reg [3:0] p = 0;

  always @(pulse) begin
    
      
    if(steps != distance) begin

  

    if(p == 4 ) begin
    
        p = 0;
        steps = steps + 1;
    
    end

    if(enable && dir) begin
        
       case(p)
        
          0 : {A, B, C, D} = {1'd1,1'd0,1'd0,1'd1};
          1 : {A, B, C, D} = {1'd1,1'd1,1'd0,1'd0};
          2 : {A, B, C, D} = {1'd0,1'd1,1'd1,1'd0};
          3 : {A, B, C, D} = {1'd0,1'd0,1'd1,1'd1};

          default: {A, B, C, D} = {1'd0,1'd0,1'd0,1'd0};
       endcase
     end 
    
     if(enable && ~dir) begin
        
        case(p)
        
          0 : {D, C, B, A} = {1'd1,1'd0,1'd0,1'd1};
          1 : {D, C, B, A} = {1'd1,1'd1,1'd0,1'd0};
          2 : {D, C, B, A} = {1'd0,1'd1,1'd1,1'd0};
          3 : {D, C, B, A} = {1'd0,1'd0,1'd1,1'd1};
          
            default: {A, B, C, D} = {1'd0,1'd0,1'd0,1'd0};
        endcase
        
     end 
    end   
     if(~enable || steps == distance) begin
     
        {A ,B ,C ,D} = {1'd0,1'd0,1'd0,1'd0};
        p = 0;
        
     end 
    p = p+1;
  end

endmodule

project3/motorcontroler/steppermotor_tb.sv
`timescale 1ns/10ps

module steppermotor_tb;

reg clk,dir,enable,reset;
integer i;

initial begin
  
  $dumpfile("steppermotor_tb.vcd");
  $dumpvars;
    
  clk = 0;
  dir = 1;
  enable = 0;

  for(i = 0; i < 1000; i = i+1) begin
    if(i > 9)begin
      enable = 1;
    end 
    if(i > 111) begin
        dir = 0;
        if( i < 131 && i > 111)begin
            enable = 0;
        end
    end
    clk = ~clk; #10;
    
  end
end
  steppermotor motor(dir,enable,clk,200);

endmodule

System_Verilog_code_base/motorcontroler/steppermotor_tb.vcd
$date
	Mon Feb  7 20:00:12 2022
$end
$version
	Icarus Verilog
$end
$timescale
	10ps
$end
$scope module steppermotor_tb $end
$var reg 1 ! clk $end
$var reg 1 " dir $end
$var reg 1 # enable $end
$var integer 32 $ i [31:0] $end
$scope module motor $end
$var wire 1 " dir $end
$var wire 32 % distance [31:0] $end
$var wire 1 # enable $end
$var wire 1 ! pulse $end
$var reg 1 & A $end
$var reg 1 ' B $end
$var reg 1 ( C $end
$var reg 1 ) D $end
$var reg 4 * p [3:0] $end
$var reg 32 + steps [31:0] $end
$upscope $end
$upscope $end
$enddefinitions $end
#0
$dumpvars
b0 +
b1 *
0)
0(
0'
0&
b11001000 %
b0 $
0#
1"
1!
$end
#1000
b1 *
0!
b1 $
#2000
b1 *
1!
b10 $
#3000
b1 *
0!
b11 $
#4000
b1 *
1!
b100 $
#5000
b1 *
0!
b101 $
#6000
b1 *
1!
b110 $
#7000
b1 *
0!
b111 $
#8000
b1 *
1!
b1000 $
#9000
b1 *
0!
b1001 $
#10000
b10 *
1&
1'
1!
1#
b1010 $
#11000
b11 *
0&
1(
0!
b1011 $
#12000
b100 *
0'
1)
1!
b1100 $
#13000
1&
0(
b1 +
b1 *
0!
b1101 $
#14000
b10 *
1'
0)
1!
b1110 $
#15000
b11 *
0&
1(
0!
b1111 $
#16000
b100 *
0'
1)
1!
b10000 $
#17000
1&
0(
b10 +
b1 *
0!
b10001 $
#18000
b10 *
1'
0)
1!
b10010 $
#19000
b11 *
0&
1(
0!
b10011 $
#20000
b100 *
0'
1)
1!
b10100 $
#21000
1&
0(
b11 +
b1 *
0!
b10101 $
#22000
b10 *
1'
0)
1!
b10110 $
#23000
b11 *
0&
1(
0!
b10111 $
#24000
b100 *
0'
1)
1!
b11000 $
#25000
1&
0(
b100 +
b1 *
0!
b11001 $
#26000
b10 *
1'
0)
1!
b11010 $
#27000
b11 *
0&
1(
0!
b11011 $
#28000
b100 *
0'
1)
1!
b11100 $
#29000
1&
0(
b101 +
b1 *
0!
b11101 $
#30000
b10 *
1'
0)
1!
b11110 $
#31000
b11 *
0&
1(
0!
b11111 $
#32000
b100 *
0'
1)
1!
b100000 $
#33000
1&
0(
b110 +
b1 *
0!
b100001 $
#34000
b10 *
1'
0)
1!
b100010 $
#35000
b11 *
0&
1(
0!
b100011 $
#36000
b100 *
0'
1)
1!
b100100 $
#37000
1&
0(
b111 +
b1 *
0!
b100101 $
#38000
b10 *
1'
0)
1!
b100110 $
#39000
b11 *
0&
1(
0!
b100111 $
#40000
b100 *
0'
1)
1!
b101000 $
#41000
1&
0(
b1000 +
b1 *
0!
b101001 $
#42000
b10 *
1'
0)
1!
b101010 $
#43000
b11 *
0&
1(
0!
b101011 $
#44000
b100 *
0'
1)
1!
b101100 $
#45000
1&
0(
b1001 +
b1 *
0!
b101101 $
#46000
b10 *
1'
0)
1!
b101110 $
#47000
b11 *
0&
1(
0!
b101111 $
#48000
b100 *
0'
1)
1!
b110000 $
#49000
1&
0(
b1010 +
b1 *
0!
b110001 $
#50000
b10 *
1'
0)
1!
b110010 $
#51000
b11 *
0&
1(
0!
b110011 $
#52000
b100 *
0'
1)
1!
b110100 $
#53000
1&
0(
b1011 +
b1 *
0!
b110101 $
#54000
b10 *
1'
0)
1!
b110110 $
#55000
b11 *
0&
1(
0!
b110111 $
#56000
b100 *
0'
1)
1!
b111000 $
#57000
1&
0(
b1100 +
b1 *
0!
b111001 $
#58000
b10 *
1'
0)
1!
b111010 $
#59000
b11 *
0&
1(
0!
b111011 $
#60000
b100 *
0'
1)
1!
b111100 $
#61000
1&
0(
b1101 +
b1 *
0!
b111101 $
#62000
b10 *
1'
0)
1!
b111110 $
#63000
b11 *
0&
1(
0!
b111111 $
#64000
b100 *
0'
1)
1!
b1000000 $
#65000
1&
0(
b1110 +
b1 *
0!
b1000001 $
#66000
b10 *
1'
0)
1!
b1000010 $
#67000
b11 *
0&
1(
0!
b1000011 $
#68000
b100 *
0'
1)
1!
b1000100 $
#69000
1&
0(
b1111 +
b1 *
0!
b1000101 $
#70000
b10 *
1'
0)
1!
b1000110 $
#71000
b11 *
0&
1(
0!
b1000111 $
#72000
b100 *
0'
1)
1!
b1001000 $
#73000
1&
0(
b10000 +
b1 *
0!
b1001001 $
#74000
b10 *
1'
0)
1!
b1001010 $
#75000
b11 *
0&
1(
0!
b1001011 $
#76000
b100 *
0'
1)
1!
b1001100 $
#77000
1&
0(
b10001 +
b1 *
0!
b1001101 $
#78000
b10 *
1'
0)
1!
b1001110 $
#79000
b11 *
0&
1(
0!
b1001111 $
#80000
b100 *
0'
1)
1!
b1010000 $
#81000
1&
0(
b10010 +
b1 *
0!
b1010001 $
#82000
b10 *
1'
0)
1!
b1010010 $
#83000
b11 *
0&
1(
0!
b1010011 $
#84000
b100 *
0'
1)
1!
b1010100 $
#85000
1&
0(
b10011 +
b1 *
0!
b1010101 $
#86000
b10 *
1'
0)
1!
b1010110 $
#87000
b11 *
0&
1(
0!
b1010111 $
#88000
b100 *
0'
1)
1!
b1011000 $
#89000
1&
0(
b10100 +
b1 *
0!
b1011001 $
#90000
b10 *
1'
0)
1!
b1011010 $
#91000
b11 *
0&
1(
0!
b1011011 $
#92000
b100 *
0'
1)
1!
b1011100 $
#93000
1&
0(
b10101 +
b1 *
0!
b1011101 $
#94000
b10 *
1'
0)
1!
b1011110 $
#95000
b11 *
0&
1(
0!
b1011111 $
#96000
b100 *
0'
1)
1!
b1100000 $
#97000
1&
0(
b10110 +
b1 *
0!
b1100001 $
#98000
b10 *
1'
0)
1!
b1100010 $
#99000
b11 *
0&
1(
0!
b1100011 $
#100000
b100 *
0'
1)
1!
b1100100 $
#101000
1&
0(
b10111 +
b1 *
0!
b1100101 $
#102000
b10 *
1'
0)
1!
b1100110 $
#103000
b11 *
0&
1(
0!
b1100111 $
#104000
b100 *
0'
1)
1!
b1101000 $
#105000
1&
0(
b11000 +
b1 *
0!
b1101001 $
#106000
b10 *
1'
0)
1!
b1101010 $
#107000
b11 *
0&
1(
0!
b1101011 $
#108000
b100 *
0'
1)
1!
b1101100 $
#109000
1&
0(
b11001 +
b1 *
0!
b1101101 $
#110000
b10 *
1'
0)
1!
b1101110 $
#111000
b11 *
0&
1(
0!
b1101111 $
#112000
b1 *
0'
0(
1!
0#
0"
b1110000 $
#113000
b1 *
0!
0#
b1110001 $
#114000
b1 *
1!
0#
b1110010 $
#115000
b1 *
0!
0#
b1110011 $
#116000
b1 *
1!
0#
b1110100 $
#117000
b1 *
0!
0#
b1110101 $
#118000
b1 *
1!
0#
b1110110 $
#119000
b1 *
0!
0#
b1110111 $
#120000
b1 *
1!
0#
b1111000 $
#121000
b1 *
0!
0#
b1111001 $
#122000
b1 *
1!
0#
b1111010 $
#123000
b1 *
0!
0#
b1111011 $
#124000
b1 *
1!
0#
b1111100 $
#125000
b1 *
0!
0#
b1111101 $
#126000
b1 *
1!
0#
b1111110 $
#127000
b1 *
0!
0#
b1111111 $
#128000
b1 *
1!
0#
b10000000 $
#129000
b1 *
0!
0#
b10000001 $
#130000
b1 *
1!
0#
b10000010 $
#131000
b10 *
1)
1(
0!
1#
b10000011 $
#132000
b11 *
0)
1'
1!
b10000100 $
#133000
b100 *
0(
1&
0!
b10000101 $
#134000
1)
0'
b11010 +
b1 *
1!
b10000110 $
#135000
b10 *
1(
0&
0!
b10000111 $
#136000
b11 *
0)
1'
1!
b10001000 $
#137000
b100 *
0(
1&
0!
b10001001 $
#138000
1)
0'
b11011 +
b1 *
1!
b10001010 $
#139000
b10 *
1(
0&
0!
b10001011 $
#140000
b11 *
0)
1'
1!
b10001100 $
#141000
b100 *
0(
1&
0!
b10001101 $
#142000
1)
0'
b11100 +
b1 *
1!
b10001110 $
#143000
b10 *
1(
0&
0!
b10001111 $
#144000
b11 *
0)
1'
1!
b10010000 $
#145000
b100 *
0(
1&
0!
b10010001 $
#146000
1)
0'
b11101 +
b1 *
1!
b10010010 $
#147000
b10 *
1(
0&
0!
b10010011 $
#148000
b11 *
0)
1'
1!
b10010100 $
#149000
b100 *
0(
1&
0!
b10010101 $
#150000
1)
0'
b11110 +
b1 *
1!
b10010110 $
#151000
b10 *
1(
0&
0!
b10010111 $
#152000
b11 *
0)
1'
1!
b10011000 $
#153000
b100 *
0(
1&
0!
b10011001 $
#154000
1)
0'
b11111 +
b1 *
1!
b10011010 $
#155000
b10 *
1(
0&
0!
b10011011 $
#156000
b11 *
0)
1'
1!
b10011100 $
#157000
b100 *
0(
1&
0!
b10011101 $
#158000
1)
0'
b100000 +
b1 *
1!
b10011110 $
#159000
b10 *
1(
0&
0!
b10011111 $
#160000
b11 *
0)
1'
1!
b10100000 $
#161000
b100 *
0(
1&
0!
b10100001 $
#162000
1)
0'
b100001 +
b1 *
1!
b10100010 $
#163000
b10 *
1(
0&
0!
b10100011 $
#164000
b11 *
0)
1'
1!
b10100100 $
#165000
b100 *
0(
1&
0!
b10100101 $
#166000
1)
0'
b100010 +
b1 *
1!
b10100110 $
#167000
b10 *
1(
0&
0!
b10100111 $
#168000
b11 *
0)
1'
1!
b10101000 $
#169000
b100 *
0(
1&
0!
b10101001 $
#170000
1)
0'
b100011 +
b1 *
1!
b10101010 $
#171000
b10 *
1(
0&
0!
b10101011 $
#172000
b11 *
0)
1'
1!
b10101100 $
#173000
b100 *
0(
1&
0!
b10101101 $
#174000
1)
0'
b100100 +
b1 *
1!
b10101110 $
#175000
b10 *
1(
0&
0!
b10101111 $
#176000
b11 *
0)
1'
1!
b10110000 $
#177000
b100 *
0(
1&
0!
b10110001 $
#178000
1)
0'
b100101 +
b1 *
1!
b10110010 $
#179000
b10 *
1(
0&
0!
b10110011 $
#180000
b11 *
0)
1'
1!
b10110100 $
#181000
b100 *
0(
1&
0!
b10110101 $
#182000
1)
0'
b100110 +
b1 *
1!
b10110110 $
#183000
b10 *
1(
0&
0!
b10110111 $
#184000
b11 *
0)
1'
1!
b10111000 $
#185000
b100 *
0(
1&
0!
b10111001 $
#186000
1)
0'
b100111 +
b1 *
1!
b10111010 $
#187000
b10 *
1(
0&
0!
b10111011 $
#188000
b11 *
0)
1'
1!
b10111100 $
#189000
b100 *
0(
1&
0!
b10111101 $
#190000
1)
0'
b101000 +
b1 *
1!
b10111110 $
#191000
b10 *
1(
0&
0!
b10111111 $
#192000
b11 *
0)
1'
1!
b11000000 $
#193000
b100 *
0(
1&
0!
b11000001 $
#194000
1)
0'
b101001 +
b1 *
1!
b11000010 $
#195000
b10 *
1(
0&
0!
b11000011 $
#196000
b11 *
0)
1'
1!
b11000100 $
#197000
b100 *
0(
1&
0!
b11000101 $
#198000
1)
0'
b101010 +
b1 *
1!
b11000110 $
#199000
b10 *
1(
0&
0!
b11000111 $
#200000
b11 *
0)
1'
1!
b11001000 $
#201000
b100 *
0(
1&
0!
b11001001 $
#202000
1)
0'
b101011 +
b1 *
1!
b11001010 $
#203000
b10 *
1(
0&
0!
b11001011 $
#204000
b11 *
0)
1'
1!
b11001100 $
#205000
b100 *
0(
1&
0!
b11001101 $
#206000
1)
0'
b101100 +
b1 *
1!
b11001110 $
#207000
b10 *
1(
0&
0!
b11001111 $
#208000
b11 *
0)
1'
1!
b11010000 $
#209000
b100 *
0(
1&
0!
b11010001 $
#210000
1)
0'
b101101 +
b1 *
1!
b11010010 $
#211000
b10 *
1(
0&
0!
b11010011 $
#212000
b11 *
0)
1'
1!
b11010100 $
#213000
b100 *
0(
1&
0!
b11010101 $
#214000
1)
0'
b101110 +
b1 *
1!
b11010110 $
#215000
b10 *
1(
0&
0!
b11010111 $
#216000
b11 *
0)
1'
1!
b11011000 $
#217000
b100 *
0(
1&
0!
b11011001 $
#218000
1)
0'
b101111 +
b1 *
1!
b11011010 $
#219000
b10 *
1(
0&
0!
b11011011 $
#220000
b11 *
0)
1'
1!
b11011100 $
#221000
b100 *
0(
1&
0!
b11011101 $
#222000
1)
0'
b110000 +
b1 *
1!
b11011110 $
#223000
b10 *
1(
0&
0!
b11011111 $
#224000
b11 *
0)
1'
1!
b11100000 $
#225000
b100 *
0(
1&
0!
b11100001 $
#226000
1)
0'
b110001 +
b1 *
1!
b11100010 $
#227000
b10 *
1(
0&
0!
b11100011 $
#228000
b11 *
0)
1'
1!
b11100100 $
#229000
b100 *
0(
1&
0!
b11100101 $
#230000
1)
0'
b110010 +
b1 *
1!
b11100110 $
#231000
b10 *
1(
0&
0!
b11100111 $
#232000
b11 *
0)
1'
1!
b11101000 $
#233000
b100 *
0(
1&
0!
b11101001 $
#234000
1)
0'
b110011 +
b1 *
1!
b11101010 $
#235000
b10 *
1(
0&
0!
b11101011 $
#236000
b11 *
0)
1'
1!
b11101100 $
#237000
b100 *
0(
1&
0!
b11101101 $
#238000
1)
0'
b110100 +
b1 *
1!
b11101110 $
#239000
b10 *
1(
0&
0!
b11101111 $
#240000
b11 *
0)
1'
1!
b11110000 $
#241000
b100 *
0(
1&
0!
b11110001 $
#242000
1)
0'
b110101 +
b1 *
1!
b11110010 $
#243000
b10 *
1(
0&
0!
b11110011 $
#244000
b11 *
0)
1'
1!
b11110100 $
#245000
b100 *
0(
1&
0!
b11110101 $
#246000
1)
0'
b110110 +
b1 *
1!
b11110110 $
#247000
b10 *
1(
0&
0!
b11110111 $
#248000
b11 *
0)
1'
1!
b11111000 $
#249000
b100 *
0(
1&
0!
b11111001 $
#250000
1)
0'
b110111 +
b1 *
1!
b11111010 $
#251000
b10 *
1(
0&
0!
b11111011 $
#252000
b11 *
0)
1'
1!
b11111100 $
#253000
b100 *
0(
1&
0!
b11111101 $
#254000
1)
0'
b111000 +
b1 *
1!
b11111110 $
#255000
b10 *
1(
0&
0!
b11111111 $
#256000
b11 *
0)
1'
1!
b100000000 $
#257000
b100 *
0(
1&
0!
b100000001 $
#258000
1)
0'
b111001 +
b1 *
1!
b100000010 $
#259000
b10 *
1(
0&
0!
b100000011 $
#260000
b11 *
0)
1'
1!
b100000100 $
#261000
b100 *
0(
1&
0!
b100000101 $
#262000
1)
0'
b111010 +
b1 *
1!
b100000110 $
#263000
b10 *
1(
0&
0!
b100000111 $
#264000
b11 *
0)
1'
1!
b100001000 $
#265000
b100 *
0(
1&
0!
b100001001 $
#266000
1)
0'
b111011 +
b1 *
1!
b100001010 $
#267000
b10 *
1(
0&
0!
b100001011 $
#268000
b11 *
0)
1'
1!
b100001100 $
#269000
b100 *
0(
1&
0!
b100001101 $
#270000
1)
0'
b111100 +
b1 *
1!
b100001110 $
#271000
b10 *
1(
0&
0!
b100001111 $
#272000
b11 *
0)
1'
1!
b100010000 $
#273000
b100 *
0(
1&
0!
b100010001 $
#274000
1)
0'
b111101 +
b1 *
1!
b100010010 $
#275000
b10 *
1(
0&
0!
b100010011 $
#276000
b11 *
0)
1'
1!
b100010100 $
#277000
b100 *
0(
1&
0!
b100010101 $
#278000
1)
0'
b111110 +
b1 *
1!
b100010110 $
#279000
b10 *
1(
0&
0!
b100010111 $
#280000
b11 *
0)
1'
1!
b100011000 $
#281000
b100 *
0(
1&
0!
b100011001 $
#282000
1)
0'
b111111 +
b1 *
1!
b100011010 $
#283000
b10 *
1(
0&
0!
b100011011 $
#284000
b11 *
0)
1'
1!
b100011100 $
#285000
b100 *
0(
1&
0!
b100011101 $
#286000
1)
0'
b1000000 +
b1 *
1!
b100011110 $
#287000
b10 *
1(
0&
0!
b100011111 $
#288000
b11 *
0)
1'
1!
b100100000 $
#289000
b100 *
0(
1&
0!
b100100001 $
#290000
1)
0'
b1000001 +
b1 *
1!
b100100010 $
#291000
b10 *
1(
0&
0!
b100100011 $
#292000
b11 *
0)
1'
1!
b100100100 $
#293000
b100 *
0(
1&
0!
b100100101 $
#294000
1)
0'
b1000010 +
b1 *
1!
b100100110 $
#295000
b10 *
1(
0&
0!
b100100111 $
#296000
b11 *
0)
1'
1!
b100101000 $
#297000
b100 *
0(
1&
0!
b100101001 $
#298000
1)
0'
b1000011 +
b1 *
1!
b100101010 $
#299000
b10 *
1(
0&
0!
b100101011 $
#300000
b11 *
0)
1'
1!
b100101100 $
#301000
b100 *
0(
1&
0!
b100101101 $
#302000
1)
0'
b1000100 +
b1 *
1!
b100101110 $
#303000
b10 *
1(
0&
0!
b100101111 $
#304000
b11 *
0)
1'
1!
b100110000 $
#305000
b100 *
0(
1&
0!
b100110001 $
#306000
1)
0'
b1000101 +
b1 *
1!
b100110010 $
#307000
b10 *
1(
0&
0!
b100110011 $
#308000
b11 *
0)
1'
1!
b100110100 $
#309000
b100 *
0(
1&
0!
b100110101 $
#310000
1)
0'
b1000110 +
b1 *
1!
b100110110 $
#311000
b10 *
1(
0&
0!
b100110111 $
#312000
b11 *
0)
1'
1!
b100111000 $
#313000
b100 *
0(
1&
0!
b100111001 $
#314000
1)
0'
b1000111 +
b1 *
1!
b100111010 $
#315000
b10 *
1(
0&
0!
b100111011 $
#316000
b11 *
0)
1'
1!
b100111100 $
#317000
b100 *
0(
1&
0!
b100111101 $
#318000
1)
0'
b1001000 +
b1 *
1!
b100111110 $
#319000
b10 *
1(
0&
0!
b100111111 $
#320000
b11 *
0)
1'
1!
b101000000 $
#321000
b100 *
0(
1&
0!
b101000001 $
#322000
1)
0'
b1001001 +
b1 *
1!
b101000010 $
#323000
b10 *
1(
0&
0!
b101000011 $
#324000
b11 *
0)
1'
1!
b101000100 $
#325000
b100 *
0(
1&
0!
b101000101 $
#326000
1)
0'
b1001010 +
b1 *
1!
b101000110 $
#327000
b10 *
1(
0&
0!
b101000111 $
#328000
b11 *
0)
1'
1!
b101001000 $
#329000
b100 *
0(
1&
0!
b101001001 $
#330000
1)
0'
b1001011 +
b1 *
1!
b101001010 $
#331000
b10 *
1(
0&
0!
b101001011 $
#332000
b11 *
0)
1'
1!
b101001100 $
#333000
b100 *
0(
1&
0!
b101001101 $
#334000
1)
0'
b1001100 +
b1 *
1!
b101001110 $
#335000
b10 *
1(
0&
0!
b101001111 $
#336000
b11 *
0)
1'
1!
b101010000 $
#337000
b100 *
0(
1&
0!
b101010001 $
#338000
1)
0'
b1001101 +
b1 *
1!
b101010010 $
#339000
b10 *
1(
0&
0!
b101010011 $
#340000
b11 *
0)
1'
1!
b101010100 $
#341000
b100 *
0(
1&
0!
b101010101 $
#342000
1)
0'
b1001110 +
b1 *
1!
b101010110 $
#343000
b10 *
1(
0&
0!
b101010111 $
#344000
b11 *
0)
1'
1!
b101011000 $
#345000
b100 *
0(
1&
0!
b101011001 $
#346000
1)
0'
b1001111 +
b1 *
1!
b101011010 $
#347000
b10 *
1(
0&
0!
b101011011 $
#348000
b11 *
0)
1'
1!
b101011100 $
#349000
b100 *
0(
1&
0!
b101011101 $
#350000
1)
0'
b1010000 +
b1 *
1!
b101011110 $
#351000
b10 *
1(
0&
0!
b101011111 $
#352000
b11 *
0)
1'
1!
b101100000 $
#353000
b100 *
0(
1&
0!
b101100001 $
#354000
1)
0'
b1010001 +
b1 *
1!
b101100010 $
#355000
b10 *
1(
0&
0!
b101100011 $
#356000
b11 *
0)
1'
1!
b101100100 $
#357000
b100 *
0(
1&
0!
b101100101 $
#358000
1)
0'
b1010010 +
b1 *
1!
b101100110 $
#359000
b10 *
1(
0&
0!
b101100111 $
#360000
b11 *
0)
1'
1!
b101101000 $
#361000
b100 *
0(
1&
0!
b101101001 $
#362000
1)
0'
b1010011 +
b1 *
1!
b101101010 $
#363000
b10 *
1(
0&
0!
b101101011 $
#364000
b11 *
0)
1'
1!
b101101100 $
#365000
b100 *
0(
1&
0!
b101101101 $
#366000
1)
0'
b1010100 +
b1 *
1!
b101101110 $
#367000
b10 *
1(
0&
0!
b101101111 $
#368000
b11 *
0)
1'
1!
b101110000 $
#369000
b100 *
0(
1&
0!
b101110001 $
#370000
1)
0'
b1010101 +
b1 *
1!
b101110010 $
#371000
b10 *
1(
0&
0!
b101110011 $
#372000
b11 *
0)
1'
1!
b101110100 $
#373000
b100 *
0(
1&
0!
b101110101 $
#374000
1)
0'
b1010110 +
b1 *
1!
b101110110 $
#375000
b10 *
1(
0&
0!
b101110111 $
#376000
b11 *
0)
1'
1!
b101111000 $
#377000
b100 *
0(
1&
0!
b101111001 $
#378000
1)
0'
b1010111 +
b1 *
1!
b101111010 $
#379000
b10 *
1(
0&
0!
b101111011 $
#380000
b11 *
0)
1'
1!
b101111100 $
#381000
b100 *
0(
1&
0!
b101111101 $
#382000
1)
0'
b1011000 +
b1 *
1!
b101111110 $
#383000
b10 *
1(
0&
0!
b101111111 $
#384000
b11 *
0)
1'
1!
b110000000 $
#385000
b100 *
0(
1&
0!
b110000001 $
#386000
1)
0'
b1011001 +
b1 *
1!
b110000010 $
#387000
b10 *
1(
0&
0!
b110000011 $
#388000
b11 *
0)
1'
1!
b110000100 $
#389000
b100 *
0(
1&
0!
b110000101 $
#390000
1)
0'
b1011010 +
b1 *
1!
b110000110 $
#391000
b10 *
1(
0&
0!
b110000111 $
#392000
b11 *
0)
1'
1!
b110001000 $
#393000
b100 *
0(
1&
0!
b110001001 $
#394000
1)
0'
b1011011 +
b1 *
1!
b110001010 $
#395000
b10 *
1(
0&
0!
b110001011 $
#396000
b11 *
0)
1'
1!
b110001100 $
#397000
b100 *
0(
1&
0!
b110001101 $
#398000
1)
0'
b1011100 +
b1 *
1!
b110001110 $
#399000
b10 *
1(
0&
0!
b110001111 $
#400000
b11 *
0)
1'
1!
b110010000 $
#401000
b100 *
0(
1&
0!
b110010001 $
#402000
1)
0'
b1011101 +
b1 *
1!
b110010010 $
#403000
b10 *
1(
0&
0!
b110010011 $
#404000
b11 *
0)
1'
1!
b110010100 $
#405000
b100 *
0(
1&
0!
b110010101 $
#406000
1)
0'
b1011110 +
b1 *
1!
b110010110 $
#407000
b10 *
1(
0&
0!
b110010111 $
#408000
b11 *
0)
1'
1!
b110011000 $
#409000
b100 *
0(
1&
0!
b110011001 $
#410000
1)
0'
b1011111 +
b1 *
1!
b110011010 $
#411000
b10 *
1(
0&
0!
b110011011 $
#412000
b11 *
0)
1'
1!
b110011100 $
#413000
b100 *
0(
1&
0!
b110011101 $
#414000
1)
0'
b1100000 +
b1 *
1!
b110011110 $
#415000
b10 *
1(
0&
0!
b110011111 $
#416000
b11 *
0)
1'
1!
b110100000 $
#417000
b100 *
0(
1&
0!
b110100001 $
#418000
1)
0'
b1100001 +
b1 *
1!
b110100010 $
#419000
b10 *
1(
0&
0!
b110100011 $
#420000
b11 *
0)
1'
1!
b110100100 $
#421000
b100 *
0(
1&
0!
b110100101 $
#422000
1)
0'
b1100010 +
b1 *
1!
b110100110 $
#423000
b10 *
1(
0&
0!
b110100111 $
#424000
b11 *
0)
1'
1!
b110101000 $
#425000
b100 *
0(
1&
0!
b110101001 $
#426000
1)
0'
b1100011 +
b1 *
1!
b110101010 $
#427000
b10 *
1(
0&
0!
b110101011 $
#428000
b11 *
0)
1'
1!
b110101100 $
#429000
b100 *
0(
1&
0!
b110101101 $
#430000
1)
0'
b1100100 +
b1 *
1!
b110101110 $
#431000
b10 *
1(
0&
0!
b110101111 $
#432000
b11 *
0)
1'
1!
b110110000 $
#433000
b100 *
0(
1&
0!
b110110001 $
#434000
1)
0'
b1100101 +
b1 *
1!
b110110010 $
#435000
b10 *
1(
0&
0!
b110110011 $
#436000
b11 *
0)
1'
1!
b110110100 $
#437000
b100 *
0(
1&
0!
b110110101 $
#438000
1)
0'
b1100110 +
b1 *
1!
b110110110 $
#439000
b10 *
1(
0&
0!
b110110111 $
#440000
b11 *
0)
1'
1!
b110111000 $
#441000
b100 *
0(
1&
0!
b110111001 $
#442000
1)
0'
b1100111 +
b1 *
1!
b110111010 $
#443000
b10 *
1(
0&
0!
b110111011 $
#444000
b11 *
0)
1'
1!
b110111100 $
#445000
b100 *
0(
1&
0!
b110111101 $
#446000
1)
0'
b1101000 +
b1 *
1!
b110111110 $
#447000
b10 *
1(
0&
0!
b110111111 $
#448000
b11 *
0)
1'
1!
b111000000 $
#449000
b100 *
0(
1&
0!
b111000001 $
#450000
1)
0'
b1101001 +
b1 *
1!
b111000010 $
#451000
b10 *
1(
0&
0!
b111000011 $
#452000
b11 *
0)
1'
1!
b111000100 $
#453000
b100 *
0(
1&
0!
b111000101 $
#454000
1)
0'
b1101010 +
b1 *
1!
b111000110 $
#455000
b10 *
1(
0&
0!
b111000111 $
#456000
b11 *
0)
1'
1!
b111001000 $
#457000
b100 *
0(
1&
0!
b111001001 $
#458000
1)
0'
b1101011 +
b1 *
1!
b111001010 $
#459000
b10 *
1(
0&
0!
b111001011 $
#460000
b11 *
0)
1'
1!
b111001100 $
#461000
b100 *
0(
1&
0!
b111001101 $
#462000
1)
0'
b1101100 +
b1 *
1!
b111001110 $
#463000
b10 *
1(
0&
0!
b111001111 $
#464000
b11 *
0)
1'
1!
b111010000 $
#465000
b100 *
0(
1&
0!
b111010001 $
#466000
1)
0'
b1101101 +
b1 *
1!
b111010010 $
#467000
b10 *
1(
0&
0!
b111010011 $
#468000
b11 *
0)
1'
1!
b111010100 $
#469000
b100 *
0(
1&
0!
b111010101 $
#470000
1)
0'
b1101110 +
b1 *
1!
b111010110 $
#471000
b10 *
1(
0&
0!
b111010111 $
#472000
b11 *
0)
1'
1!
b111011000 $
#473000
b100 *
0(
1&
0!
b111011001 $
#474000
1)
0'
b1101111 +
b1 *
1!
b111011010 $
#475000
b10 *
1(
0&
0!
b111011011 $
#476000
b11 *
0)
1'
1!
b111011100 $
#477000
b100 *
0(
1&
0!
b111011101 $
#478000
1)
0'
b1110000 +
b1 *
1!
b111011110 $
#479000
b10 *
1(
0&
0!
b111011111 $
#480000
b11 *
0)
1'
1!
b111100000 $
#481000
b100 *
0(
1&
0!
b111100001 $
#482000
1)
0'
b1110001 +
b1 *
1!
b111100010 $
#483000
b10 *
1(
0&
0!
b111100011 $
#484000
b11 *
0)
1'
1!
b111100100 $
#485000
b100 *
0(
1&
0!
b111100101 $
#486000
1)
0'
b1110010 +
b1 *
1!
b111100110 $
#487000
b10 *
1(
0&
0!
b111100111 $
#488000
b11 *
0)
1'
1!
b111101000 $
#489000
b100 *
0(
1&
0!
b111101001 $
#490000
1)
0'
b1110011 +
b1 *
1!
b111101010 $
#491000
b10 *
1(
0&
0!
b111101011 $
#492000
b11 *
0)
1'
1!
b111101100 $
#493000
b100 *
0(
1&
0!
b111101101 $
#494000
1)
0'
b1110100 +
b1 *
1!
b111101110 $
#495000
b10 *
1(
0&
0!
b111101111 $
#496000
b11 *
0)
1'
1!
b111110000 $
#497000
b100 *
0(
1&
0!
b111110001 $
#498000
1)
0'
b1110101 +
b1 *
1!
b111110010 $
#499000
b10 *
1(
0&
0!
b111110011 $
#500000
b11 *
0)
1'
1!
b111110100 $
#501000
b100 *
0(
1&
0!
b111110101 $
#502000
1)
0'
b1110110 +
b1 *
1!
b111110110 $
#503000
b10 *
1(
0&
0!
b111110111 $
#504000
b11 *
0)
1'
1!
b111111000 $
#505000
b100 *
0(
1&
0!
b111111001 $
#506000
1)
0'
b1110111 +
b1 *
1!
b111111010 $
#507000
b10 *
1(
0&
0!
b111111011 $
#508000
b11 *
0)
1'
1!
b111111100 $
#509000
b100 *
0(
1&
0!
b111111101 $
#510000
1)
0'
b1111000 +
b1 *
1!
b111111110 $
#511000
b10 *
1(
0&
0!
b111111111 $
#512000
b11 *
0)
1'
1!
b1000000000 $
#513000
b100 *
0(
1&
0!
b1000000001 $
#514000
1)
0'
b1111001 +
b1 *
1!
b1000000010 $
#515000
b10 *
1(
0&
0!
b1000000011 $
#516000
b11 *
0)
1'
1!
b1000000100 $
#517000
b100 *
0(
1&
0!
b1000000101 $
#518000
1)
0'
b1111010 +
b1 *
1!
b1000000110 $
#519000
b10 *
1(
0&
0!
b1000000111 $
#520000
b11 *
0)
1'
1!
b1000001000 $
