System_Verilog_code_base/FSM/LED.sv
module LED(input clk,enable,dbstate, output reg Y);

reg [1:0]led;

always @(posedge clk) begin

    if(enable) begin
        
        case(dbstate)
        
            0 : {led[1], led[0],Y } = {1'b1,  1'b0, 1'b0};
            
            1 : {led[0] , led[1] , Y} = {1'b1, 1'b0 , 1'b1};
         
            
        endcase
        
        
    end

end


endmodule

System_Verilog_code_base/FSM/database.sv
module database(input clk, enable, input [3:0] code, output reg done);

    reg [3:0] ROM[15:0];
    reg [3:0]checksum = 0;

    always @(clk) begin
      
      if(enable)begin
            ROM[0] = 4'b0000;   //wasser
            ROM[1] = 4'b0001;   //cola
            ROM[2] = 4'b0010;   //orange
            ROM[3] = 4'b0011;   //zitrone
            ROM[4] = 4'b0100;   //tee
            ROM[5] = 4'b0101;   //kaffe
            ROM[6] = 4'b0110;   //cappucino
            ROM[7] = 4'b0111;   //latte macchiato
            ROM[8] = 4'b1000;   //wasser mit eis
            ROM[9] = 4'b1001;   //cola mit eis
            ROM[10] = 4'b1010;  //orange mit eis
            ROM[11] = 4'b1011;  //zitrone mit ein
            ROM[12] = 4'b1100;  //tee mit zucker
            ROM[13] = 4'b1101;  //kaffe mit zucker
            ROM[14] = 4'b1110;  //cappucino mit zucker
            ROM[15] = 4'b1111;  //latte macchiato mit zucker
            
            
            if(checksum == 15) begin
                checksum <= 0;
            end 
            else begin
            
                checksum  = checksum + 1;
            end
            
            if(code == ROM[checksum]) done = 1;
            else done  = 0;
                
            
        end
    end

endmodule

project3/FSM/beep.sv
module beep(input clk, enable, output reg Y);

reg [5:0] delay;

always @(posedge clk) begin
    
    if(enable) begin
        
        delay = delay + 1;
        
        if(delay == 50) Y = 1;
        
    end
    
    else begin
     
    delay = 0; 
    Y = 0;
    
    end
    
end

endmodule

project3/FSM/scanner.sv
module scanner(input clk,enable, input[3:0] code,output reg code_valid);


reg [3:0] validation;
reg [3:0] hardcopy;

always @(posedge clk) begin
    
    if(enable) begin
    
        validation[hardcopy] = code[hardcopy];
        
        if(validation[hardcopy] == 1'bx)begin
            
            code_valid = 0;
        end
        else begin
        
            if(hardcopy == 4)begin
             code_valid = 1;
            end       
        
        hardcopy = hardcopy +1;
        end
    end
    
    else begin
     
        hardcopy = 0;
        code_valid = 0;
        
     end;

end

endmodule

project3/FSM/decoder_2x4.sv
module decoder_2x4(input wire [1:0] ps, output wire[3:0]y);

assign y[0] = (~ps[0]) & (~ps[1]);
assign y[1] = (~ps[0]) & ps[1];
assign y[2] = ps[0] & (~ps[1]);
assign y[3] = ps[0] & ps[1];

endmodule

project3/FSM/station_if.sv
module station_if(input reset , clk, enable, input [3:0] code, output Y);

    wire [3:0] cm;
    reg [1:0] ps;
    reg [1:0] ns;
    reg [1:0] scan = 2'b00 , beep = 2'b10 , db = 2'b01 , led = 2'b11;
    wire dbstate,beepstate,ledlights,scanner;
    
    always @(clk) begin
       
        if(reset) ps = scan;
        else ps = ns;
        
        case(ps)
           
           scan : if(scanner) ns = beep;
                  else ns = scan;
                  
           beep : if(beepstate) ns = db;
                  else ns = beep;
                  
           //feedback loop from LED to database      
            
           db : if(dbstate) ns = led;
                else ns = led;
                
           led : if(ledlights) ns = scan;
                 else ns = db;
           
           default: ns = scan; 
       endcase
        
   end
   
    decoder_2x4 decoder(ps,cm);
    scanner scanmod(clk,cm[0],code,scanner);
    beep beeper(clk,cm[1],beepstate);
    database dbs(clk,cm[2],code,dbstate);
    LED leds(clk,cm[3],dbstate,ledlights);

endmodule

System_Verilog_code_base/FSM/station_if_tb.sv
`timescale 1ns/10ps
module station_if_tb;

reg [3:0] code;
reg clk,reset,enable;
wire Y;

integer i;

    initial begin
    
        code = 4'b1101;
        clk = 0;
        reset = 0;
        enable = 1;
        
        $dumpfile("station_if_tb.vcd");
        $dumpvars;
    
        for(i = 0 ; i < 500 ; i = i +1)begin
            clk = ~clk; #10;
        end
    
       
    end
    
   
    station_if uut(reset,clk,enable,code,Y);

endmodule

project3/FSM/station_if_tb.vcd
$date
	Sun Feb 13 13:26:32 2022
$end
$version
	Icarus Verilog
$end
$timescale
	10ps
$end
$scope module station_if_tb $end
$var wire 1 ! Y $end
$var reg 1 " clk $end
$var reg 4 # code [3:0] $end
$var reg 1 $ enable $end
$var reg 1 % reset $end
$var integer 32 & i [31:0] $end
$scope module uut $end
$var wire 1 ! Y $end
$var wire 1 " clk $end
$var wire 4 ' code [3:0] $end
$var wire 1 $ enable $end
$var wire 1 % reset $end
$var wire 1 ( scanner $end
$var wire 1 ) ledlights $end
$var wire 1 * dbstate $end
$var wire 4 + cm [3:0] $end
$var wire 1 , beepstate $end
$var reg 2 - beep [1:0] $end
$var reg 2 . db [1:0] $end
$var reg 2 / led [1:0] $end
$var reg 2 0 ns [1:0] $end
$var reg 2 1 ps [1:0] $end
$var reg 2 2 scan [1:0] $end
$scope module beeper $end
$var wire 1 " clk $end
$var wire 1 3 enable $end
$var reg 1 , Y $end
$var reg 6 4 delay [5:0] $end
$upscope $end
$scope module dbs $end
$var wire 1 " clk $end
$var wire 4 5 code [3:0] $end
$var wire 1 6 enable $end
$var reg 4 7 checksum [3:0] $end
$var reg 1 * done $end
$upscope $end
$scope module decoder $end
$var wire 2 8 ps [1:0] $end
$var wire 4 9 y [3:0] $end
$upscope $end
$scope module leds $end
$var wire 1 " clk $end
$var wire 1 * dbstate $end
$var wire 1 : enable $end
$var reg 1 ) Y $end
$var reg 2 ; led [1:0] $end
$upscope $end
$scope module scanmod $end
$var wire 1 " clk $end
$var wire 4 < code [3:0] $end
$var wire 1 = enable $end
$var reg 1 ( code_valid $end
$var reg 4 > hardcopy [3:0] $end
$var reg 4 ? validation [3:0] $end
$upscope $end
$upscope $end
$upscope $end
$enddefinitions $end
#0
$dumpvars
bx ?
b0 >
x=
b1101 <
bx ;
x:
bx 9
bx 8
b0 7
x6
b1101 5
b0 4
x3
b0 2
bx 1
b0 0
b11 /
b1 .
b10 -
0,
bx +
x*
x)
0(
b1101 '
b0 &
0%
1$
b1101 #
1"
z!
$end
#1000
1=
03
06
0:
b1 +
b1 9
b0 1
b0 8
0"
b1 &
#2000
b1 >
bx1 ?
1"
b10 &
#3000
0"
b11 &
#4000
b10 >
bx01 ?
1"
b100 &
#5000
0"
b101 &
#6000
b11 >
bx101 ?
1"
b110 &
#7000
0"
b111 &
#8000
b100 >
b1101 ?
1"
b1000 &
#9000
0"
b1001 &
#10000
b101 >
1(
1"
b1010 &
#11000
b10 0
0"
b1011 &
#12000
0=
13
b10 +
b10 9
b110 >
b10 1
b10 8
1"
b1100 &
#13000
0"
b1101 &
#14000
b1 4
0(
b0 >
1"
b1110 &
#15000
0"
b1111 &
#16000
b10 4
1"
b10000 &
#17000
0"
b10001 &
#18000
b11 4
1"
b10010 &
#19000
0"
b10011 &
#20000
b100 4
1"
b10100 &
#21000
0"
b10101 &
#22000
b101 4
1"
b10110 &
#23000
0"
b10111 &
#24000
b110 4
1"
b11000 &
#25000
0"
b11001 &
#26000
b111 4
1"
b11010 &
#27000
0"
b11011 &
#28000
b1000 4
1"
b11100 &
#29000
0"
b11101 &
#30000
b1001 4
1"
b11110 &
#31000
0"
b11111 &
#32000
b1010 4
1"
b100000 &
#33000
0"
b100001 &
#34000
b1011 4
1"
b100010 &
#35000
0"
b100011 &
#36000
b1100 4
1"
b100100 &
#37000
0"
b100101 &
#38000
b1101 4
1"
b100110 &
#39000
0"
b100111 &
#40000
b1110 4
1"
b101000 &
#41000
0"
b101001 &
#42000
b1111 4
1"
b101010 &
#43000
0"
b101011 &
#44000
b10000 4
1"
b101100 &
#45000
0"
b101101 &
#46000
b10001 4
1"
b101110 &
#47000
0"
b101111 &
#48000
b10010 4
1"
b110000 &
#49000
0"
b110001 &
#50000
b10011 4
1"
b110010 &
#51000
0"
b110011 &
#52000
b10100 4
1"
b110100 &
#53000
0"
b110101 &
#54000
b10101 4
1"
b110110 &
#55000
0"
b110111 &
#56000
b10110 4
1"
b111000 &
#57000
0"
b111001 &
#58000
b10111 4
1"
b111010 &
#59000
0"
b111011 &
#60000
b11000 4
1"
b111100 &
#61000
0"
b111101 &
#62000
b11001 4
1"
b111110 &
#63000
0"
b111111 &
#64000
b11010 4
1"
b1000000 &
#65000
0"
b1000001 &
#66000
b11011 4
1"
b1000010 &
#67000
0"
b1000011 &
#68000
b11100 4
1"
b1000100 &
#69000
0"
b1000101 &
#70000
b11101 4
1"
b1000110 &
#71000
0"
b1000111 &
#72000
b11110 4
1"
b1001000 &
#73000
0"
b1001001 &
#74000
b11111 4
1"
b1001010 &
#75000
0"
b1001011 &
#76000
b100000 4
1"
b1001100 &
#77000
0"
b1001101 &
#78000
b100001 4
1"
b1001110 &
#79000
0"
b1001111 &
#80000
b100010 4
1"
b1010000 &
#81000
0"
b1010001 &
#82000
b100011 4
1"
b1010010 &
#83000
0"
b1010011 &
#84000
b100100 4
1"
b1010100 &
#85000
0"
b1010101 &
#86000
b100101 4
1"
b1010110 &
#87000
0"
b1010111 &
#88000
b100110 4
1"
b1011000 &
#89000
0"
b1011001 &
#90000
b100111 4
1"
b1011010 &
#91000
0"
b1011011 &
#92000
b101000 4
1"
b1011100 &
#93000
0"
b1011101 &
#94000
b101001 4
1"
b1011110 &
#95000
0"
b1011111 &
#96000
b101010 4
1"
b1100000 &
#97000
0"
b1100001 &
#98000
b101011 4
1"
b1100010 &
#99000
0"
b1100011 &
#100000
b101100 4
1"
b1100100 &
#101000
0"
b1100101 &
#102000
b101101 4
1"
b1100110 &
#103000
0"
b1100111 &
#104000
b101110 4
1"
b1101000 &
#105000
0"
b1101001 &
#106000
b101111 4
1"
b1101010 &
#107000
0"
b1101011 &
#108000
b110000 4
1"
b1101100 &
#109000
0"
b1101101 &
#110000
b110001 4
1"
b1101110 &
#111000
0"
b1101111 &
#112000
1,
b110010 4
1"
b1110000 &
#113000
b1 0
0"
b1110001 &
#114000
03
16
b100 +
b100 9
b110011 4
b11 0
b1 1
b1 8
1"
b1110010 &
#115000
06
1:
b1000 +
b1000 9
0*
b1 7
b1 0
b11 1
b11 8
0"
b1110011 &
#116000
16
0:
b100 +
b100 9
0,
b0 4
b10 ;
0)
b11 0
b1 1
b1 8
1"
b1110100 &
#117000
06
1:
b1000 +
b1000 9
b10 7
b1 0
b11 1
b11 8
0"
b1110101 &
#118000
16
0:
b100 +
b100 9
b11 0
b1 1
b1 8
1"
b1110110 &
#119000
06
1:
b1000 +
b1000 9
b11 7
b1 0
b11 1
b11 8
0"
b1110111 &
#120000
16
0:
b100 +
b100 9
b11 0
b1 1
b1 8
1"
b1111000 &
#121000
06
1:
b1000 +
b1000 9
b100 7
b1 0
b11 1
b11 8
0"
b1111001 &
#122000
16
0:
b100 +
b100 9
b11 0
b1 1
b1 8
1"
b1111010 &
#123000
06
1:
b1000 +
b1000 9
b101 7
b1 0
b11 1
b11 8
0"
b1111011 &
#124000
16
0:
b100 +
b100 9
b11 0
b1 1
b1 8
1"
b1111100 &
#125000
06
1:
b1000 +
b1000 9
b110 7
b1 0
b11 1
b11 8
0"
b1111101 &
#126000
16
0:
b100 +
b100 9
b11 0
b1 1
b1 8
1"
b1111110 &
#127000
06
1:
b1000 +
b1000 9
b111 7
b1 0
b11 1
b11 8
0"
b1111111 &
#128000
16
0:
b100 +
b100 9
b11 0
b1 1
b1 8
1"
b10000000 &
#129000
06
1:
b1000 +
b1000 9
b1000 7
b1 0
b11 1
b11 8
0"
b10000001 &
#130000
16
0:
b100 +
b100 9
b11 0
b1 1
b1 8
1"
b10000010 &
#131000
06
1:
b1000 +
b1000 9
b1001 7
b1 0
b11 1
b11 8
0"
b10000011 &
#132000
16
0:
b100 +
b100 9
b11 0
b1 1
b1 8
1"
b10000100 &
#133000
06
1:
b1000 +
b1000 9
b1010 7
b1 0
b11 1
b11 8
0"
b10000101 &
#134000
16
0:
b100 +
b100 9
b11 0
b1 1
b1 8
1"
b10000110 &
#135000
06
1:
b1000 +
b1000 9
b1011 7
b1 0
b11 1
b11 8
0"
b10000111 &
#136000
16
0:
b100 +
b100 9
b11 0
b1 1
b1 8
1"
b10001000 &
#137000
06
1:
b1000 +
b1000 9
b1100 7
b1 0
b11 1
b11 8
0"
b10001001 &
#138000
16
0:
b100 +
b100 9
b11 0
b1 1
b1 8
1"
b10001010 &
#139000
06
1:
b1000 +
b1000 9
1*
b1101 7
b1 0
b11 1
b11 8
0"
b10001011 &
#140000
16
0:
b100 +
b100 9
b1 ;
1)
b11 0
b1 1
b1 8
1"
b10001100 &
#141000
06
1:
b1000 +
b1000 9
0*
b1110 7
b0 0
b11 1
b11 8
0"
b10001101 &
#142000
1=
0:
b1 +
b1 9
b10 ;
0)
b0 1
b0 8
1"
b10001110 &
#143000
0"
b10001111 &
#144000
b1 >
1"
b10010000 &
#145000
0"
b10010001 &
#146000
b10 >
1"
b10010010 &
#147000
0"
b10010011 &
#148000
b11 >
1"
b10010100 &
#149000
0"
b10010101 &
#150000
b100 >
1"
b10010110 &
#151000
0"
b10010111 &
#152000
b101 >
1(
1"
b10011000 &
#153000
b10 0
0"
b10011001 &
#154000
0=
13
b10 +
b10 9
b110 >
b10 1
b10 8
1"
b10011010 &
#155000
0"
b10011011 &
#156000
0(
b0 >
b1 4
1"
b10011100 &
#157000
0"
b10011101 &
#158000
b10 4
1"
b10011110 &
#159000
0"
b10011111 &
#160000
b11 4
1"
b10100000 &
#161000
0"
b10100001 &
#162000
b100 4
1"
b10100010 &
#163000
0"
b10100011 &
#164000
b101 4
1"
b10100100 &
#165000
0"
b10100101 &
#166000
b110 4
1"
b10100110 &
#167000
0"
b10100111 &
#168000
b111 4
1"
b10101000 &
#169000
0"
b10101001 &
#170000
b1000 4
1"
b10101010 &
#171000
0"
b10101011 &
#172000
b1001 4
1"
b10101100 &
#173000
0"
b10101101 &
#174000
b1010 4
1"
b10101110 &
#175000
0"
b10101111 &
#176000
b1011 4
1"
b10110000 &
#177000
0"
b10110001 &
#178000
b1100 4
1"
b10110010 &
#179000
0"
b10110011 &
#180000
b1101 4
1"
b10110100 &
#181000
0"
b10110101 &
#182000
b1110 4
1"
b10110110 &
#183000
0"
b10110111 &
#184000
b1111 4
1"
b10111000 &
#185000
0"
b10111001 &
#186000
b10000 4
1"
b10111010 &
#187000
0"
b10111011 &
#188000
b10001 4
1"
b10111100 &
#189000
0"
b10111101 &
#190000
b10010 4
1"
b10111110 &
#191000
0"
b10111111 &
#192000
b10011 4
1"
b11000000 &
#193000
0"
b11000001 &
#194000
b10100 4
1"
b11000010 &
#195000
0"
b11000011 &
#196000
b10101 4
1"
b11000100 &
#197000
0"
b11000101 &
#198000
b10110 4
1"
b11000110 &
#199000
0"
b11000111 &
#200000
b10111 4
1"
b11001000 &
#201000
0"
b11001001 &
#202000
b11000 4
1"
b11001010 &
#203000
0"
b11001011 &
#204000
b11001 4
1"
b11001100 &
#205000
0"
b11001101 &
#206000
b11010 4
1"
b11001110 &
#207000
0"
b11001111 &
#208000
b11011 4
1"
b11010000 &
#209000
0"
b11010001 &
#210000
b11100 4
1"
b11010010 &
#211000
0"
b11010011 &
#212000
b11101 4
1"
b11010100 &
#213000
0"
b11010101 &
#214000
b11110 4
1"
b11010110 &
#215000
0"
b11010111 &
#216000
b11111 4
1"
b11011000 &
#217000
0"
b11011001 &
#218000
b100000 4
1"
b11011010 &
#219000
0"
b11011011 &
#220000
b100001 4
1"
b11011100 &
#221000
0"
b11011101 &
#222000
b100010 4
1"
b11011110 &
#223000
0"
b11011111 &
#224000
b100011 4
1"
b11100000 &
#225000
0"
b11100001 &
#226000
b100100 4
1"
b11100010 &
#227000
0"
b11100011 &
#228000
b100101 4
1"
b11100100 &
#229000
0"
b11100101 &
#230000
b100110 4
1"
b11100110 &
#231000
0"
b11100111 &
#232000
b100111 4
1"
b11101000 &
#233000
0"
b11101001 &
#234000
b101000 4
1"
b11101010 &
#235000
0"
b11101011 &
#236000
b101001 4
1"
b11101100 &
#237000
0"
b11101101 &
#238000
b101010 4
1"
b11101110 &
#239000
0"
b11101111 &
#240000
b101011 4
1"
b11110000 &
#241000
0"
b11110001 &
#242000
b101100 4
1"
b11110010 &
#243000
0"
b11110011 &
#244000
b101101 4
1"
b11110100 &
#245000
0"
b11110101 &
#246000
b101110 4
1"
b11110110 &
#247000
0"
b11110111 &
#248000
b101111 4
1"
b11111000 &
#249000
0"
b11111001 &
#250000
b110000 4
1"
b11111010 &
#251000
0"
b11111011 &
#252000
b110001 4
1"
b11111100 &
#253000
0"
b11111101 &
#254000
1,
b110010 4
1"
b11111110 &
#255000
b1 0
0"
b11111111 &
#256000
03
16
b100 +
b100 9
b110011 4
b11 0
b1 1
b1 8
1"
b100000000 &
#257000
06
1:
b1000 +
b1000 9
b1111 7
b1 0
b11 1
b11 8
0"
b100000001 &
#258000
16
0:
b100 +
b100 9
0,
b0 4
b11 0
b1 1
b1 8
1"
b100000010 &
#259000
b0 7
06
1:
b1000 +
b1000 9
b1 0
b11 1
b11 8
0"
b100000011 &
#260000
16
0:
b100 +
b100 9
b11 0
b1 1
b1 8
1"
b100000100 &
#261000
06
1:
b1000 +
b1000 9
b1 7
b1 0
b11 1
b11 8
0"
b100000101 &
#262000
16
0:
b100 +
b100 9
b11 0
b1 1
b1 8
1"
b100000110 &
#263000
06
1:
b1000 +
b1000 9
b10 7
b1 0
b11 1
b11 8
0"
b100000111 &
#264000
16
0:
b100 +
b100 9
b11 0
b1 1
b1 8
1"
b100001000 &
#265000
06
1:
b1000 +
b1000 9
b11 7
b1 0
b11 1
b11 8
0"
b100001001 &
#266000
16
0:
b100 +
b100 9
b11 0
b1 1
b1 8
1"
b100001010 &
#267000
06
1:
b1000 +
b1000 9
b100 7
b1 0
b11 1
b11 8
0"
b100001011 &
#268000
16
0:
b100 +
b100 9
b11 0
b1 1
b1 8
1"
b100001100 &
#269000
06
1:
b1000 +
b1000 9
b101 7
b1 0
b11 1
b11 8
0"
b100001101 &
#270000
16
0:
b100 +
b100 9
b11 0
b1 1
b1 8
1"
b100001110 &
#271000
06
1:
b1000 +
b1000 9
b110 7
b1 0
b11 1
b11 8
0"
b100001111 &
#272000
16
0:
b100 +
b100 9
b11 0
b1 1
b1 8
1"
b100010000 &
#273000
06
1:
b1000 +
b1000 9
b111 7
b1 0
b11 1
b11 8
0"
b100010001 &
#274000
16
0:
b100 +
b100 9
b11 0
b1 1
b1 8
1"
b100010010 &
#275000
06
1:
b1000 +
b1000 9
b1000 7
b1 0
b11 1
b11 8
0"
b100010011 &
#276000
16
0:
b100 +
b100 9
b11 0
b1 1
b1 8
1"
b100010100 &
#277000
06
1:
b1000 +
b1000 9
b1001 7
b1 0
b11 1
b11 8
0"
b100010101 &
#278000
16
0:
b100 +
b100 9
b11 0
b1 1
b1 8
1"
b100010110 &
#279000
06
1:
b1000 +
b1000 9
b1010 7
b1 0
b11 1
b11 8
0"
b100010111 &
#280000
16
0:
b100 +
b100 9
b11 0
b1 1
b1 8
1"
b100011000 &
#281000
06
1:
b1000 +
b1000 9
b1011 7
b1 0
b11 1
b11 8
0"
b100011001 &
#282000
16
0:
b100 +
b100 9
b11 0
b1 1
b1 8
1"
b100011010 &
#283000
06
1:
b1000 +
b1000 9
b1100 7
b1 0
b11 1
b11 8
0"
b100011011 &
#284000
16
0:
b100 +
b100 9
b11 0
b1 1
b1 8
1"
b100011100 &
#285000
06
1:
b1000 +
b1000 9
1*
b1101 7
b1 0
b11 1
b11 8
0"
b100011101 &
#286000
16
0:
b100 +
b100 9
b1 ;
1)
b11 0
b1 1
b1 8
1"
b100011110 &
#287000
06
1:
b1000 +
b1000 9
0*
b1110 7
b0 0
b11 1
b11 8
0"
b100011111 &
#288000
1=
0:
b1 +
b1 9
b10 ;
0)
b0 1
b0 8
1"
b100100000 &
#289000
0"
b100100001 &
#290000
b1 >
1"
b100100010 &
#291000
0"
b100100011 &
#292000
b10 >
1"
b100100100 &
#293000
0"
b100100101 &
#294000
b11 >
1"
b100100110 &
#295000
0"
b100100111 &
#296000
b100 >
1"
b100101000 &
#297000
0"
b100101001 &
#298000
b101 >
1(
1"
b100101010 &
#299000
b10 0
0"
b100101011 &
#300000
0=
13
b10 +
b10 9
b110 >
b10 1
b10 8
1"
b100101100 &
#301000
0"
b100101101 &
#302000
b1 4
0(
b0 >
1"
b100101110 &
#303000
0"
b100101111 &
#304000
b10 4
1"
b100110000 &
#305000
0"
b100110001 &
#306000
b11 4
1"
b100110010 &
#307000
0"
b100110011 &
#308000
b100 4
1"
b100110100 &
#309000
0"
b100110101 &
#310000
b101 4
1"
b100110110 &
#311000
0"
b100110111 &
#312000
b110 4
1"
b100111000 &
#313000
0"
b100111001 &
#314000
b111 4
1"
b100111010 &
#315000
0"
b100111011 &
#316000
b1000 4
1"
b100111100 &
#317000
0"
b100111101 &
#318000
b1001 4
1"
b100111110 &
#319000
0"
b100111111 &
#320000
b1010 4
1"
b101000000 &
#321000
0"
b101000001 &
#322000
b1011 4
1"
b101000010 &
#323000
0"
b101000011 &
#324000
b1100 4
1"
b101000100 &
#325000
0"
b101000101 &
#326000
b1101 4
1"
b101000110 &
#327000
0"
b101000111 &
#328000
b1110 4
1"
b101001000 &
#329000
0"
b101001001 &
#330000
b1111 4
1"
b101001010 &
#331000
0"
b101001011 &
#332000
b10000 4
1"
b101001100 &
#333000
0"
b101001101 &
#334000
b10001 4
1"
b101001110 &
#335000
0"
b101001111 &
#336000
b10010 4
1"
b101010000 &
#337000
0"
b101010001 &
#338000
b10011 4
1"
b101010010 &
#339000
0"
b101010011 &
#340000
b10100 4
1"
b101010100 &
#341000
0"
b101010101 &
#342000
b10101 4
1"
b101010110 &
#343000
0"
b101010111 &
#344000
b10110 4
1"
b101011000 &
#345000
0"
b101011001 &
#346000
b10111 4
1"
b101011010 &
#347000
0"
b101011011 &
#348000
b11000 4
1"
b101011100 &
#349000
0"
b101011101 &
#350000
b11001 4
1"
b101011110 &
#351000
0"
b101011111 &
#352000
b11010 4
1"
b101100000 &
#353000
0"
b101100001 &
#354000
b11011 4
1"
b101100010 &
#355000
0"
b101100011 &
#356000
b11100 4
1"
b101100100 &
#357000
0"
b101100101 &
#358000
b11101 4
1"
b101100110 &
#359000
0"
b101100111 &
#360000
b11110 4
1"
b101101000 &
#361000
0"
b101101001 &
#362000
b11111 4
1"
b101101010 &
#363000
0"
b101101011 &
#364000
b100000 4
1"
b101101100 &
#365000
0"
b101101101 &
#366000
b100001 4
1"
b101101110 &
#367000
0"
b101101111 &
#368000
b100010 4
1"
b101110000 &
#369000
0"
b101110001 &
#370000
b100011 4
1"
b101110010 &
#371000
0"
b101110011 &
#372000
b100100 4
1"
b101110100 &
#373000
0"
b101110101 &
#374000
b100101 4
1"
b101110110 &
#375000
0"
b101110111 &
#376000
b100110 4
1"
b101111000 &
#377000
0"
b101111001 &
#378000
b100111 4
1"
b101111010 &
#379000
0"
b101111011 &
#380000
b101000 4
1"
b101111100 &
#381000
0"
b101111101 &
#382000
b101001 4
1"
b101111110 &
#383000
0"
b101111111 &
#384000
b101010 4
1"
b110000000 &
#385000
0"
b110000001 &
#386000
b101011 4
1"
b110000010 &
#387000
0"
b110000011 &
#388000
b101100 4
1"
b110000100 &
#389000
0"
b110000101 &
#390000
b101101 4
1"
b110000110 &
#391000
0"
b110000111 &
#392000
b101110 4
1"
b110001000 &
#393000
0"
b110001001 &
#394000
b101111 4
1"
b110001010 &
#395000
0"
b110001011 &
#396000
b110000 4
1"
b110001100 &
#397000
0"
b110001101 &
#398000
b110001 4
1"
b110001110 &
#399000
0"
b110001111 &
#400000
1,
b110010 4
1"
b110010000 &
#401000
b1 0
0"
b110010001 &
#402000
03
16
b100 +
b100 9
b110011 4
b11 0
b1 1
b1 8
1"
b110010010 &
#403000
06
1:
b1000 +
b1000 9
b1111 7
b1 0
b11 1
b11 8
0"
b110010011 &
#404000
16
0:
b100 +
b100 9
0,
b0 4
b11 0
b1 1
b1 8
1"
b110010100 &
#405000
b0 7
06
1:
b1000 +
b1000 9
b1 0
b11 1
b11 8
0"
b110010101 &
#406000
16
0:
b100 +
b100 9
b11 0
b1 1
b1 8
1"
b110010110 &
#407000
06
1:
b1000 +
b1000 9
b1 7
b1 0
b11 1
b11 8
0"
b110010111 &
#408000
16
0:
b100 +
b100 9
b11 0
b1 1
b1 8
1"
b110011000 &
#409000
06
1:
b1000 +
b1000 9
b10 7
b1 0
b11 1
b11 8
0"
b110011001 &
#410000
16
0:
b100 +
b100 9
b11 0
b1 1
b1 8
1"
b110011010 &
#411000
06
1:
b1000 +
b1000 9
b11 7
b1 0
b11 1
b11 8
0"
b110011011 &
#412000
16
0:
b100 +
b100 9
b11 0
b1 1
b1 8
1"
b110011100 &
#413000
06
1:
b1000 +
b1000 9
b100 7
b1 0
b11 1
b11 8
0"
b110011101 &
#414000
16
0:
b100 +
b100 9
b11 0
b1 1
b1 8
1"
b110011110 &
#415000
06
1:
b1000 +
b1000 9
b101 7
b1 0
b11 1
b11 8
0"
b110011111 &
#416000
16
0:
b100 +
b100 9
b11 0
b1 1
b1 8
1"
b110100000 &
#417000
06
1:
b1000 +
b1000 9
b110 7
b1 0
b11 1
b11 8
0"
b110100001 &
#418000
16
0:
b100 +
b100 9
b11 0
b1 1
b1 8
1"
b110100010 &
#419000
06
1:
b1000 +
b1000 9
b111 7
b1 0
b11 1
b11 8
0"
b110100011 &
#420000
16
0:
b100 +
b100 9
b11 0
b1 1
b1 8
1"
b110100100 &
#421000
06
1:
b1000 +
b1000 9
b1000 7
b1 0
b11 1
b11 8
0"
b110100101 &
#422000
16
0:
b100 +
b100 9
b11 0
b1 1
b1 8
1"
b110100110 &
#423000
06
1:
b1000 +
b1000 9
b1001 7
b1 0
b11 1
b11 8
0"
b110100111 &
#424000
16
0:
b100 +
b100 9
b11 0
b1 1
b1 8
1"
b110101000 &
#425000
06
1:
b1000 +
b1000 9
b1010 7
b1 0
b11 1
b11 8
0"
b110101001 &
#426000
16
0:
b100 +
b100 9
b11 0
b1 1
b1 8
1"
b110101010 &
#427000
06
1:
b1000 +
b1000 9
b1011 7
b1 0
b11 1
b11 8
0"
b110101011 &
#428000
16
0:
b100 +
b100 9
b11 0
b1 1
b1 8
1"
b110101100 &
#429000
06
1:
b1000 +
b1000 9
b1100 7
b1 0
b11 1
b11 8
0"
b110101101 &
#430000
16
0:
b100 +
b100 9
b11 0
b1 1
b1 8
1"
b110101110 &
#431000
06
1:
b1000 +
b1000 9
1*
b1101 7
b1 0
b11 1
b11 8
0"
b110101111 &
#432000
16
0:
b100 +
b100 9
b1 ;
1)
b11 0
b1 1
b1 8
1"
b110110000 &
#433000
06
1:
b1000 +
b1000 9
0*
b1110 7
b0 0
b11 1
b11 8
0"
b110110001 &
#434000
1=
0:
b1 +
b1 9
b10 ;
0)
b0 1
b0 8
1"
b110110010 &
#435000
0"
b110110011 &
#436000
b1 >
1"
b110110100 &
#437000
0"
b110110101 &
#438000
b10 >
1"
b110110110 &
#439000
0"
b110110111 &
#440000
b11 >
1"
b110111000 &
#441000
0"
b110111001 &
#442000
b100 >
1"
b110111010 &
#443000
0"
b110111011 &
#444000
b101 >
1(
1"
b110111100 &
#445000
b10 0
0"
b110111101 &
#446000
0=
13
b10 +
b10 9
b110 >
b10 1
b10 8
1"
b110111110 &
#447000
0"
b110111111 &
#448000
0(
b0 >
b1 4
1"
b111000000 &
#449000
0"
b111000001 &
#450000
b10 4
1"
b111000010 &
#451000
0"
b111000011 &
#452000
b11 4
1"
b111000100 &
#453000
0"
b111000101 &
#454000
b100 4
1"
b111000110 &
#455000
0"
b111000111 &
#456000
b101 4
1"
b111001000 &
#457000
0"
b111001001 &
#458000
b110 4
1"
b111001010 &
#459000
0"
b111001011 &
#460000
b111 4
1"
b111001100 &
#461000
0"
b111001101 &
#462000
b1000 4
1"
b111001110 &
#463000
0"
b111001111 &
#464000
b1001 4
1"
b111010000 &
#465000
0"
b111010001 &
#466000
b1010 4
1"
b111010010 &
#467000
0"
b111010011 &
#468000
b1011 4
1"
b111010100 &
#469000
0"
b111010101 &
#470000
b1100 4
1"
b111010110 &
#471000
0"
b111010111 &
#472000
b1101 4
1"
b111011000 &
#473000
0"
b111011001 &
#474000
b1110 4
1"
b111011010 &
#475000
0"
b111011011 &
#476000
b1111 4
1"
b111011100 &
#477000
0"
b111011101 &
#478000
b10000 4
1"
b111011110 &
#479000
0"
b111011111 &
#480000
b10001 4
1"
b111100000 &
#481000
0"
b111100001 &
#482000
b10010 4
1"
b111100010 &
#483000
0"
b111100011 &
#484000
b10011 4
1"
b111100100 &
#485000
0"
b111100101 &
#486000
b10100 4
1"
b111100110 &
#487000
0"
b111100111 &
#488000
b10101 4
1"
b111101000 &
#489000
0"
b111101001 &
#490000
b10110 4
1"
b111101010 &
#491000
0"
b111101011 &
#492000
b10111 4
1"
b111101100 &
#493000
0"
b111101101 &
#494000
b11000 4
1"
b111101110 &
#495000
0"
b111101111 &
#496000
b11001 4
1"
b111110000 &
#497000
0"
b111110001 &
#498000
b11010 4
1"
b111110010 &
#499000
0"
b111110011 &
#500000
b111110100 &
